[
 {
  "buying": 0,
  "docstatus": 0,
  "doctype": "Email Template",
  "hr": 0,
  "modified": "2023-04-17 23:22:25.346062",
  "name": "Exit Questionnaire Notification",
  "response": "<h2>Exit Questionnaire</h2>\n<br>\n\n<p>\n\tDear {{ employee_name }},\n\t<br><br>\n\n\tThank you for the contribution you have made during your time at {{ company }}. We value your opinion and welcome the feedback on your experience working with us.\n\tRequest you to take out a few minutes to fill up this Exit Questionnaire.\n\n\t{% set web_form = frappe.db.get_value('HR Settings', 'HR Settings', 'exit_questionnaire_web_form') %}\n\t{% set web_form_link = frappe.utils.get_url(uri=frappe.db.get_value('Web Form', web_form, 'route')) %}\n\n\t<br><br>\n\t<a class=\"btn btn-primary\" href=\"{{ web_form_link }}\" target=\"_blank\">{{ _('Submit Now') }}</a>\n</p>\n",
  "response_html": "",
  "selling": 0,
  "subject": "Exit Questionnaire - Submission",
  "use_html": 0
 },
 {
  "buying": 0,
  "docstatus": 0,
  "doctype": "Email Template",
  "hr": 0,
  "modified": "2023-07-17 11:13:58.101786",
  "name": "Leave Approval Notification",
  "response": "<div class=\"ql-editor read-mode\"><h1>Leave Application Notification</h1><h3>Details:</h3><table class=\"table table-bordered\"><tbody><tr><td data-row=\"1\">Employee</td><td data-row=\"1\">{{employee_name}}</td></tr><tr><td data-row=\"2\">Leave Type</td><td data-row=\"2\">{{leave_type}}</td></tr><tr><td data-row=\"3\">From Date</td><td data-row=\"3\">{{from_date}}</td></tr><tr><td data-row=\"4\">To Date</td><td data-row=\"4\">{{to_date}}</td></tr><tr><td data-row=\"5\">Status</td><td data-row=\"5\">{{status}}</td></tr></tbody></table></div>",
  "response_html": "\n    <h1>Leave Application Notification</h1>\n        <p>Hello,<br>\n            {{employee_name}} has applied for {{leave_type}}. Kindly, check the details below.\n        </p>\n        \n        <table class=\"table table-condensed table-bordered\">\n          <tr>\n            <th class=\"text-center\">Employee</th>\n            <th class=\"text-center\">{{employee_name}}</th>\n          </tr>\n          <tr>\n            <th class=\"text-center\">Leave Type</th>\n            <th class=\"text-center\">{{leave_type}}</th>\n          </tr>\n          <tr>\n            <th class=\"text-center\">Reason</th>\n            <th class=\"text-center\">{{description}}</th>\n          </tr>\n          <tr>\n            <th class=\"text-center\">From Date</th>\n            <th class=\"text-center\">{{from_date}}</th>\n          </tr>\n          <tr>\n            <th class=\"text-center\">To Date</th>\n            <th class=\"text-center\">{{to_date}}</th>\n          </tr>\n        </table>\n        <div style=\"text-align:center; padding: 5px\">\n             <a class=\"btn btn-success\" style=\"background-color:dodgerblue;text-align:center;\" href=\"{{ base_url }}/api/method/one_fm.api.mobile.Leave_application.leave_notify?docname={{name}}&amp;status=Approved\">\n            Approve</a>\n            <a class=\"btn btn-danger\" style=\"background-color:Gray;text-align:center;\" href=\"{{ base_url }}/api/method/one_fm.api.mobile.Leave_application.leave_notify?docname={{name}}&amp;status=Rejected\">\n                Reject</a>  \n        </div>",
  "selling": 0,
  "subject": "Leave Application - Approval",
  "use_html": 1
 },
 {
  "buying": 0,
  "docstatus": 0,
  "doctype": "Email Template",
  "hr": 0,
  "modified": "2024-10-22 19:07:28.854023",
  "name": "Leave Status Notification",
  "response": "<div class=\"ql-editor read-mode\"><pre class=\"ql-code-block-container\" spellcheck=\"false\"><div class=\"ql-code-block\" data-language=\"plain\">&lt;html&gt;</div><div class=\"ql-code-block\" data-language=\"plain\">&lt;head&gt;</div><div class=\"ql-code-block\" data-language=\"plain\"> &nbsp; &nbsp;&lt;meta content=\"text/html; charset=UTF-8\" http-equiv=\"content-type\"&gt;</div><div class=\"ql-code-block\" data-language=\"plain\"> &nbsp; &nbsp;&lt;style type=\"text/css\"&gt;@import url(https://themes.googleusercontent.com/fonts/css?kit=dpiI8CyVsrzWsJLBFKehGpLhv3qFjX7dUn1mYxfCXhI);</div><div class=\"ql-code-block\" data-language=\"plain\"><br></div><div class=\"ql-code-block\" data-language=\"plain\"> &nbsp; &nbsp;ul.lst-kix_g0ncveqa373c-5 {</div><div class=\"ql-code-block\" data-language=\"plain\"> &nbsp; &nbsp; &nbsp; &nbsp;list-style-type: none</div><div class=\"ql-code-block\" data-language=\"plain\"> &nbsp; &nbsp;}</div><div class=\"ql-code-block\" data-language=\"plain\"><br></div><div class=\"ql-code-block\" data-language=\"plain\"> &nbsp; &nbsp;.lst-kix_8uqlpnf6wjap-8 &gt; li:before {</div><div class=\"ql-code-block\" data-language=\"plain\"> &nbsp; &nbsp; &nbsp; &nbsp;content: \"\\0025a0 &nbsp; \"</div><div class=\"ql-code-block\" data-language=\"plain\"> &nbsp; &nbsp;}</div><div class=\"ql-code-block\" data-language=\"plain\"><br></div><div class=\"ql-code-block\" data-language=\"plain\"> &nbsp; &nbsp;ul.lst-kix_g0ncveqa373c-4 {</div><div class=\"ql-code-block\" data-language=\"plain\"> &nbsp; &nbsp; &nbsp; &nbsp;list-style-type: none</div><div class=\"ql-code-block\" data-language=\"plain\"> &nbsp; &nbsp;}</div><div class=\"ql-code-block\" data-language=\"plain\"><br></div><div class=\"ql-code-block\" data-language=\"plain\"> &nbsp; &nbsp;ul.lst-kix_g0ncveqa373c-7 {</div><div class=\"ql-code-block\" data-language=\"plain\"> &nbsp; &nbsp; &nbsp; &nbsp;list-style-type: none</div><div class=\"ql-code-block\" data-language=\"plain\"> &nbsp; &nbsp;}</div><div class=\"ql-code-block\" data-language=\"plain\"><br></div><div class=\"ql-code-block\" data-language=\"plain\"> &nbsp; &nbsp;.lst-kix_8uqlpnf6wjap-7 &gt; li:before {</div><div class=\"ql-code-block\" data-language=\"plain\"> &nbsp; &nbsp; &nbsp; &nbsp;content: \"\\0025cb &nbsp; \"</div><div class=\"ql-code-block\" data-language=\"plain\"> &nbsp; &nbsp;}</div><div class=\"ql-code-block\" data-language=\"plain\"><br></div><div class=\"ql-code-block\" data-language=\"plain\"> &nbsp; &nbsp;ul.lst-kix_g0ncveqa373c-6 {</div><div class=\"ql-code-block\" data-language=\"plain\"> &nbsp; &nbsp; &nbsp; &nbsp;list-style-type: none</div><div class=\"ql-code-block\" data-language=\"plain\"> &nbsp; &nbsp;}</div><div class=\"ql-code-block\" data-language=\"plain\"><br></div><div class=\"ql-code-block\" data-language=\"plain\"> &nbsp; &nbsp;ul.lst-kix_g0ncveqa373c-1 {</div><div class=\"ql-code-block\" data-language=\"plain\"> &nbsp; &nbsp; &nbsp; &nbsp;list-style-type: none</div><div class=\"ql-code-block\" data-language=\"plain\"> &nbsp; &nbsp;}</div><div class=\"ql-code-block\" data-language=\"plain\"><br></div><div class=\"ql-code-block\" data-language=\"plain\"> &nbsp; &nbsp;.lst-kix_8uqlpnf6wjap-6 &gt; li:before {</div><div class=\"ql-code-block\" data-language=\"plain\"> &nbsp; &nbsp; &nbsp; &nbsp;content: \"\\0025cf &nbsp; \"</div><div class=\"ql-code-block\" data-language=\"plain\"> &nbsp; &nbsp;}</div><div class=\"ql-code-block\" data-language=\"plain\"><br></div><div class=\"ql-code-block\" data-language=\"plain\"> &nbsp; &nbsp;ul.lst-kix_g0ncveqa373c-0 {</div><div class=\"ql-code-block\" data-language=\"plain\"> &nbsp; &nbsp; &nbsp; &nbsp;list-style-type: none</div><div class=\"ql-code-block\" data-language=\"plain\"> &nbsp; &nbsp;}</div><div class=\"ql-code-block\" data-language=\"plain\"><br></div><div class=\"ql-code-block\" data-language=\"plain\"> &nbsp; &nbsp;ul.lst-kix_g0ncveqa373c-3 {</div><div class=\"ql-code-block\" data-language=\"plain\"> &nbsp; &nbsp; &nbsp; &nbsp;list-style-type: none</div><div class=\"ql-code-block\" data-language=\"plain\"> &nbsp; &nbsp;}</div><div class=\"ql-code-block\" data-language=\"plain\"><br></div><div class=\"ql-code-block\" data-language=\"plain\"> &nbsp; &nbsp;ul.lst-kix_g0ncveqa373c-2 {</div><div class=\"ql-code-block\" data-language=\"plain\"> &nbsp; &nbsp; &nbsp; &nbsp;list-style-type: none</div><div class=\"ql-code-block\" data-language=\"plain\"> &nbsp; &nbsp;}</div><div class=\"ql-code-block\" data-language=\"plain\"><br></div><div class=\"ql-code-block\" data-language=\"plain\"> &nbsp; &nbsp;.lst-kix_g0ncveqa373c-0 &gt; li:before {</div><div class=\"ql-code-block\" data-language=\"plain\"> &nbsp; &nbsp; &nbsp; &nbsp;content: \"\\0025cf &nbsp; \"</div><div class=\"ql-code-block\" data-language=\"plain\"> &nbsp; &nbsp;}</div><div class=\"ql-code-block\" data-language=\"plain\"><br></div><div class=\"ql-code-block\" data-language=\"plain\"> &nbsp; &nbsp;.lst-kix_8uqlpnf6wjap-4 &gt; li:before {</div><div class=\"ql-code-block\" data-language=\"plain\"> &nbsp; &nbsp; &nbsp; &nbsp;content: \"\\0025cb &nbsp; \"</div><div class=\"ql-code-block\" data-language=\"plain\"> &nbsp; &nbsp;}</div><div class=\"ql-code-block\" data-language=\"plain\"><br></div><div class=\"ql-code-block\" data-language=\"plain\"> &nbsp; &nbsp;.lst-kix_8uqlpnf6wjap-3 &gt; li:before {</div><div class=\"ql-code-block\" data-language=\"plain\"> &nbsp; &nbsp; &nbsp; &nbsp;content: \"\\0025cf &nbsp; \"</div><div class=\"ql-code-block\" data-language=\"plain\"> &nbsp; &nbsp;}</div><div class=\"ql-code-block\" data-language=\"plain\"><br></div><div class=\"ql-code-block\" data-language=\"plain\"> &nbsp; &nbsp;.lst-kix_8uqlpnf6wjap-5 &gt; li:before {</div><div class=\"ql-code-block\" data-language=\"plain\"> &nbsp; &nbsp; &nbsp; &nbsp;content: \"\\0025a0 &nbsp; \"</div><div class=\"ql-code-block\" data-language=\"plain\"> &nbsp; &nbsp;}</div><div class=\"ql-code-block\" data-language=\"plain\"><br></div><div class=\"ql-code-block\" data-language=\"plain\"> &nbsp; &nbsp;.lst-kix_g0ncveqa373c-2 &gt; li:before {</div><div class=\"ql-code-block\" data-language=\"plain\"> &nbsp; &nbsp; &nbsp; &nbsp;content: \"\\0025a0 &nbsp; \"</div><div class=\"ql-code-block\" data-language=\"plain\"> &nbsp; &nbsp;}</div><div class=\"ql-code-block\" data-language=\"plain\"><br></div><div class=\"ql-code-block\" data-language=\"plain\"> &nbsp; &nbsp;ul.lst-kix_g0ncveqa373c-8 {</div><div class=\"ql-code-block\" data-language=\"plain\"> &nbsp; &nbsp; &nbsp; &nbsp;list-style-type: none</div><div class=\"ql-code-block\" data-language=\"plain\"> &nbsp; &nbsp;}</div><div class=\"ql-code-block\" data-language=\"plain\"><br></div><div class=\"ql-code-block\" data-language=\"plain\"> &nbsp; &nbsp;.lst-kix_g0ncveqa373c-1 &gt; li:before {</div><div class=\"ql-code-block\" data-language=\"plain\"> &nbsp; &nbsp; &nbsp; &nbsp;content: \"\\0025cb &nbsp; \"</div><div class=\"ql-code-block\" data-language=\"plain\"> &nbsp; &nbsp;}</div><div class=\"ql-code-block\" data-language=\"plain\"><br></div><div class=\"ql-code-block\" data-language=\"plain\"> &nbsp; &nbsp;.lst-kix_g0ncveqa373c-4 &gt; li:before {</div><div class=\"ql-code-block\" data-language=\"plain\"> &nbsp; &nbsp; &nbsp; &nbsp;content: \"\\0025cb &nbsp; \"</div><div class=\"ql-code-block\" data-language=\"plain\"> &nbsp; &nbsp;}</div><div class=\"ql-code-block\" data-language=\"plain\"><br></div><div class=\"ql-code-block\" data-language=\"plain\"> &nbsp; &nbsp;.lst-kix_8uqlpnf6wjap-0 &gt; li:before {</div><div class=\"ql-code-block\" data-language=\"plain\"> &nbsp; &nbsp; &nbsp; &nbsp;content: \"\\0025cf &nbsp; \"</div><div class=\"ql-code-block\" data-language=\"plain\"> &nbsp; &nbsp;}</div><div class=\"ql-code-block\" data-language=\"plain\"><br></div><div class=\"ql-code-block\" data-language=\"plain\"> &nbsp; &nbsp;.lst-kix_8uqlpnf6wjap-1 &gt; li:before {</div><div class=\"ql-code-block\" data-language=\"plain\"> &nbsp; &nbsp; &nbsp; &nbsp;content: \"\\0025cb &nbsp; \"</div><div class=\"ql-code-block\" data-language=\"plain\"> &nbsp; &nbsp;}</div><div class=\"ql-code-block\" data-language=\"plain\"><br></div><div class=\"ql-code-block\" data-language=\"plain\"> &nbsp; &nbsp;.lst-kix_8uqlpnf6wjap-2 &gt; li:before {</div><div class=\"ql-code-block\" data-language=\"plain\"> &nbsp; &nbsp; &nbsp; &nbsp;content: \"\\0025a0 &nbsp; \"</div><div class=\"ql-code-block\" data-language=\"plain\"> &nbsp; &nbsp;}</div><div class=\"ql-code-block\" data-language=\"plain\"><br></div><div class=\"ql-code-block\" data-language=\"plain\"> &nbsp; &nbsp;.lst-kix_g0ncveqa373c-3 &gt; li:before {</div><div class=\"ql-code-block\" data-language=\"plain\"> &nbsp; &nbsp; &nbsp; &nbsp;content: \"\\0025cf &nbsp; \"</div><div class=\"ql-code-block\" data-language=\"plain\"> &nbsp; &nbsp;}</div><div class=\"ql-code-block\" data-language=\"plain\"><br></div><div class=\"ql-code-block\" data-language=\"plain\"> &nbsp; &nbsp;.lst-kix_g0ncveqa373c-7 &gt; li:before {</div><div class=\"ql-code-block\" data-language=\"plain\"> &nbsp; &nbsp; &nbsp; &nbsp;content: \"\\0025cb &nbsp; \"</div><div class=\"ql-code-block\" data-language=\"plain\"> &nbsp; &nbsp;}</div><div class=\"ql-code-block\" data-language=\"plain\"><br></div><div class=\"ql-code-block\" data-language=\"plain\"> &nbsp; &nbsp;.lst-kix_g0ncveqa373c-6 &gt; li:before {</div><div class=\"ql-code-block\" data-language=\"plain\"> &nbsp; &nbsp; &nbsp; &nbsp;content: \"\\0025cf &nbsp; \"</div><div class=\"ql-code-block\" data-language=\"plain\"> &nbsp; &nbsp;}</div><div class=\"ql-code-block\" data-language=\"plain\"><br></div><div class=\"ql-code-block\" data-language=\"plain\"> &nbsp; &nbsp;.lst-kix_g0ncveqa373c-5 &gt; li:before {</div><div class=\"ql-code-block\" data-language=\"plain\"> &nbsp; &nbsp; &nbsp; &nbsp;content: \"\\0025a0 &nbsp; \"</div><div class=\"ql-code-block\" data-language=\"plain\"> &nbsp; &nbsp;}</div><div class=\"ql-code-block\" data-language=\"plain\"><br></div><div class=\"ql-code-block\" data-language=\"plain\"> &nbsp; &nbsp;li.li-bullet-1:before {</div><div class=\"ql-code-block\" data-language=\"plain\"> &nbsp; &nbsp; &nbsp; &nbsp;white-space: nowrap;</div><div class=\"ql-code-block\" data-language=\"plain\"> &nbsp; &nbsp; &nbsp; &nbsp;display: inline-block;</div><div class=\"ql-code-block\" data-language=\"plain\"> &nbsp; &nbsp; &nbsp; &nbsp;min-width: 18pt;</div><div class=\"ql-code-block\" data-language=\"plain\"> &nbsp; &nbsp; &nbsp; &nbsp;margin-right: 18pt</div><div class=\"ql-code-block\" data-language=\"plain\"> &nbsp; &nbsp;}</div><div class=\"ql-code-block\" data-language=\"plain\"><br></div><div class=\"ql-code-block\" data-language=\"plain\"> &nbsp; &nbsp;.lst-kix_g0ncveqa373c-8 &gt; li:before {</div><div class=\"ql-code-block\" data-language=\"plain\"> &nbsp; &nbsp; &nbsp; &nbsp;content: \"\\0025a0 &nbsp; \"</div><div class=\"ql-code-block\" data-language=\"plain\"> &nbsp; &nbsp;}</div><div class=\"ql-code-block\" data-language=\"plain\"><br></div><div class=\"ql-code-block\" data-language=\"plain\"> &nbsp; &nbsp;li.li-bullet-0:before {</div><div class=\"ql-code-block\" data-language=\"plain\"> &nbsp; &nbsp; &nbsp; &nbsp;margin-left: -18pt;</div><div class=\"ql-code-block\" data-language=\"plain\"> &nbsp; &nbsp; &nbsp; &nbsp;white-space: nowrap;</div><div class=\"ql-code-block\" data-language=\"plain\"> &nbsp; &nbsp; &nbsp; &nbsp;display: inline-block;</div><div class=\"ql-code-block\" data-language=\"plain\"> &nbsp; &nbsp; &nbsp; &nbsp;min-width: 18pt</div><div class=\"ql-code-block\" data-language=\"plain\"> &nbsp; &nbsp;}</div><div class=\"ql-code-block\" data-language=\"plain\"><br></div><div class=\"ql-code-block\" data-language=\"plain\"> &nbsp; &nbsp;li.li-bullet-2:before {</div><div class=\"ql-code-block\" data-language=\"plain\"> &nbsp; &nbsp; &nbsp; &nbsp;white-space: nowrap;</div><div class=\"ql-code-block\" data-language=\"plain\"> &nbsp; &nbsp; &nbsp; &nbsp;display: inline-block;</div><div class=\"ql-code-block\" data-language=\"plain\"> &nbsp; &nbsp; &nbsp; &nbsp;min-width: 18pt;</div><div class=\"ql-code-block\" data-language=\"plain\"> &nbsp; &nbsp; &nbsp; &nbsp;margin-right: 18pt</div><div class=\"ql-code-block\" data-language=\"plain\"> &nbsp; &nbsp;}</div><div class=\"ql-code-block\" data-language=\"plain\"><br></div><div class=\"ql-code-block\" data-language=\"plain\"> &nbsp; &nbsp;ul.lst-kix_8uqlpnf6wjap-0 {</div><div class=\"ql-code-block\" data-language=\"plain\"> &nbsp; &nbsp; &nbsp; &nbsp;list-style-type: none</div><div class=\"ql-code-block\" data-language=\"plain\"> &nbsp; &nbsp;}</div><div class=\"ql-code-block\" data-language=\"plain\"><br></div><div class=\"ql-code-block\" data-language=\"plain\"> &nbsp; &nbsp;ul.lst-kix_8uqlpnf6wjap-2 {</div><div class=\"ql-code-block\" data-language=\"plain\"> &nbsp; &nbsp; &nbsp; &nbsp;list-style-type: none</div><div class=\"ql-code-block\" data-language=\"plain\"> &nbsp; &nbsp;}</div><div class=\"ql-code-block\" data-language=\"plain\"><br></div><div class=\"ql-code-block\" data-language=\"plain\"> &nbsp; &nbsp;ul.lst-kix_8uqlpnf6wjap-1 {</div><div class=\"ql-code-block\" data-language=\"plain\"> &nbsp; &nbsp; &nbsp; &nbsp;list-style-type: none</div><div class=\"ql-code-block\" data-language=\"plain\"> &nbsp; &nbsp;}</div><div class=\"ql-code-block\" data-language=\"plain\"><br></div><div class=\"ql-code-block\" data-language=\"plain\"> &nbsp; &nbsp;ul.lst-kix_8uqlpnf6wjap-4 {</div><div class=\"ql-code-block\" data-language=\"plain\"> &nbsp; &nbsp; &nbsp; &nbsp;list-style-type: none</div><div class=\"ql-code-block\" data-language=\"plain\"> &nbsp; &nbsp;}</div><div class=\"ql-code-block\" data-language=\"plain\"><br></div><div class=\"ql-code-block\" data-language=\"plain\"> &nbsp; &nbsp;ul.lst-kix_8uqlpnf6wjap-3 {</div><div class=\"ql-code-block\" data-language=\"plain\"> &nbsp; &nbsp; &nbsp; &nbsp;list-style-type: none</div><div class=\"ql-code-block\" data-language=\"plain\"> &nbsp; &nbsp;}</div><div class=\"ql-code-block\" data-language=\"plain\"><br></div><div class=\"ql-code-block\" data-language=\"plain\"> &nbsp; &nbsp;ul.lst-kix_8uqlpnf6wjap-6 {</div><div class=\"ql-code-block\" data-language=\"plain\"> &nbsp; &nbsp; &nbsp; &nbsp;list-style-type: none</div><div class=\"ql-code-block\" data-language=\"plain\"> &nbsp; &nbsp;}</div><div class=\"ql-code-block\" data-language=\"plain\"><br></div><div class=\"ql-code-block\" data-language=\"plain\"> &nbsp; &nbsp;ul.lst-kix_8uqlpnf6wjap-5 {</div><div class=\"ql-code-block\" data-language=\"plain\"> &nbsp; &nbsp; &nbsp; &nbsp;list-style-type: none</div><div class=\"ql-code-block\" data-language=\"plain\"> &nbsp; &nbsp;}</div><div class=\"ql-code-block\" data-language=\"plain\"><br></div><div class=\"ql-code-block\" data-language=\"plain\"> &nbsp; &nbsp;ul.lst-kix_8uqlpnf6wjap-8 {</div><div class=\"ql-code-block\" data-language=\"plain\"> &nbsp; &nbsp; &nbsp; &nbsp;list-style-type: none</div><div class=\"ql-code-block\" data-language=\"plain\"> &nbsp; &nbsp;}</div><div class=\"ql-code-block\" data-language=\"plain\"><br></div><div class=\"ql-code-block\" data-language=\"plain\"> &nbsp; &nbsp;ul.lst-kix_8uqlpnf6wjap-7 {</div><div class=\"ql-code-block\" data-language=\"plain\"> &nbsp; &nbsp; &nbsp; &nbsp;list-style-type: none</div><div class=\"ql-code-block\" data-language=\"plain\"> &nbsp; &nbsp;}</div><div class=\"ql-code-block\" data-language=\"plain\"><br></div><div class=\"ql-code-block\" data-language=\"plain\"> &nbsp; &nbsp;ol {</div><div class=\"ql-code-block\" data-language=\"plain\"> &nbsp; &nbsp; &nbsp; &nbsp;margin: 0;</div><div class=\"ql-code-block\" data-language=\"plain\"> &nbsp; &nbsp; &nbsp; &nbsp;padding: 0</div><div class=\"ql-code-block\" data-language=\"plain\"> &nbsp; &nbsp;}</div><div class=\"ql-code-block\" data-language=\"plain\"><br></div><div class=\"ql-code-block\" data-language=\"plain\"> &nbsp; &nbsp;table td, table th {</div><div class=\"ql-code-block\" data-language=\"plain\"> &nbsp; &nbsp; &nbsp; &nbsp;padding: 0</div><div class=\"ql-code-block\" data-language=\"plain\"> &nbsp; &nbsp;}</div><div class=\"ql-code-block\" data-language=\"plain\"><br></div><div class=\"ql-code-block\" data-language=\"plain\"> &nbsp; &nbsp;.c8 {</div><div class=\"ql-code-block\" data-language=\"plain\"> &nbsp; &nbsp; &nbsp; &nbsp;border-right-style: solid;</div><div class=\"ql-code-block\" data-language=\"plain\"> &nbsp; &nbsp; &nbsp; &nbsp;padding: 5pt 5pt 5pt 5pt;</div><div class=\"ql-code-block\" data-language=\"plain\"> &nbsp; &nbsp; &nbsp; &nbsp;border-bottom-color: #ffffff;</div><div class=\"ql-code-block\" data-language=\"plain\"> &nbsp; &nbsp; &nbsp; &nbsp;border-top-width: 1pt;</div><div class=\"ql-code-block\" data-language=\"plain\"> &nbsp; &nbsp; &nbsp; &nbsp;border-right-width: 1pt;</div><div class=\"ql-code-block\" data-language=\"plain\"> &nbsp; &nbsp; &nbsp; &nbsp;border-left-color: #ffffff;</div><div class=\"ql-code-block\" data-language=\"plain\"> &nbsp; &nbsp; &nbsp; &nbsp;vertical-align: top;</div><div class=\"ql-code-block\" data-language=\"plain\"> &nbsp; &nbsp; &nbsp; &nbsp;border-right-color: #ffffff;</div><div class=\"ql-code-block\" data-language=\"plain\"> &nbsp; &nbsp; &nbsp; &nbsp;border-left-width: 1pt;</div><div class=\"ql-code-block\" data-language=\"plain\"> &nbsp; &nbsp; &nbsp; &nbsp;border-top-style: solid;</div><div class=\"ql-code-block\" data-language=\"plain\"> &nbsp; &nbsp; &nbsp; &nbsp;border-left-style: solid;</div><div class=\"ql-code-block\" data-language=\"plain\"> &nbsp; &nbsp; &nbsp; &nbsp;border-bottom-width: 1pt;</div><div class=\"ql-code-block\" data-language=\"plain\"> &nbsp; &nbsp; &nbsp; &nbsp;width: 234pt;</div><div class=\"ql-code-block\" data-language=\"plain\"> &nbsp; &nbsp; &nbsp; &nbsp;border-top-color: #ffffff;</div><div class=\"ql-code-block\" data-language=\"plain\"> &nbsp; &nbsp; &nbsp; &nbsp;border-bottom-style: solid</div><div class=\"ql-code-block\" data-language=\"plain\"> &nbsp; &nbsp;}</div><div class=\"ql-code-block\" data-language=\"plain\"><br></div><div class=\"ql-code-block\" data-language=\"plain\"> &nbsp; &nbsp;.c5 {</div><div class=\"ql-code-block\" data-language=\"plain\"> &nbsp; &nbsp; &nbsp; &nbsp;margin-left: 36pt;</div><div class=\"ql-code-block\" data-language=\"plain\"> &nbsp; &nbsp; &nbsp; &nbsp;padding-top: 12pt;</div><div class=\"ql-code-block\" data-language=\"plain\"> &nbsp; &nbsp; &nbsp; &nbsp;padding-left: 0pt;</div><div class=\"ql-code-block\" data-language=\"plain\"> &nbsp; &nbsp; &nbsp; &nbsp;padding-bottom: 12pt;</div><div class=\"ql-code-block\" data-language=\"plain\"> &nbsp; &nbsp; &nbsp; &nbsp;line-height: 1.15;</div><div class=\"ql-code-block\" data-language=\"plain\"> &nbsp; &nbsp; &nbsp; &nbsp;orphans: 2;</div><div class=\"ql-code-block\" data-language=\"plain\"> &nbsp; &nbsp; &nbsp; &nbsp;widows: 2;</div><div class=\"ql-code-block\" data-language=\"plain\"> &nbsp; &nbsp; &nbsp; &nbsp;text-align: left</div><div class=\"ql-code-block\" data-language=\"plain\"> &nbsp; &nbsp;}</div><div class=\"ql-code-block\" data-language=\"plain\"><br></div><div class=\"ql-code-block\" data-language=\"plain\"> &nbsp; &nbsp;.c0 {</div><div class=\"ql-code-block\" data-language=\"plain\"> &nbsp; &nbsp; &nbsp; &nbsp;background-color: #ffffff;</div><div class=\"ql-code-block\" data-language=\"plain\"> &nbsp; &nbsp; &nbsp; &nbsp;color: #000000;</div><div class=\"ql-code-block\" data-language=\"plain\"> &nbsp; &nbsp; &nbsp; &nbsp;font-weight: 400;</div><div class=\"ql-code-block\" data-language=\"plain\"> &nbsp; &nbsp; &nbsp; &nbsp;text-decoration: none;</div><div class=\"ql-code-block\" data-language=\"plain\"> &nbsp; &nbsp; &nbsp; &nbsp;vertical-align: baseline;</div><div class=\"ql-code-block\" data-language=\"plain\"> &nbsp; &nbsp; &nbsp; &nbsp;font-size: 11pt;</div><div class=\"ql-code-block\" data-language=\"plain\"> &nbsp; &nbsp; &nbsp; &nbsp;font-family: \"Roboto\";</div><div class=\"ql-code-block\" data-language=\"plain\"> &nbsp; &nbsp; &nbsp; &nbsp;font-style: normal</div><div class=\"ql-code-block\" data-language=\"plain\"> &nbsp; &nbsp;}</div><div class=\"ql-code-block\" data-language=\"plain\"><br></div><div class=\"ql-code-block\" data-language=\"plain\"> &nbsp; &nbsp;.c4 {</div><div class=\"ql-code-block\" data-language=\"plain\"> &nbsp; &nbsp; &nbsp; &nbsp;color: #434343;</div><div class=\"ql-code-block\" data-language=\"plain\"> &nbsp; &nbsp; &nbsp; &nbsp;font-weight: 400;</div><div class=\"ql-code-block\" data-language=\"plain\"> &nbsp; &nbsp; &nbsp; &nbsp;text-decoration: none;</div><div class=\"ql-code-block\" data-language=\"plain\"> &nbsp; &nbsp; &nbsp; &nbsp;vertical-align: baseline;</div><div class=\"ql-code-block\" data-language=\"plain\"> &nbsp; &nbsp; &nbsp; &nbsp;font-size: 14pt;</div><div class=\"ql-code-block\" data-language=\"plain\"> &nbsp; &nbsp; &nbsp; &nbsp;font-family: \"Arial\";</div><div class=\"ql-code-block\" data-language=\"plain\"> &nbsp; &nbsp; &nbsp; &nbsp;font-style: normal</div><div class=\"ql-code-block\" data-language=\"plain\"> &nbsp; &nbsp;}</div><div class=\"ql-code-block\" data-language=\"plain\"><br></div><div class=\"ql-code-block\" data-language=\"plain\"> &nbsp; &nbsp;.c1 {</div><div class=\"ql-code-block\" data-language=\"plain\"> &nbsp; &nbsp; &nbsp; &nbsp;padding-top: 0pt;</div><div class=\"ql-code-block\" data-language=\"plain\"> &nbsp; &nbsp; &nbsp; &nbsp;padding-bottom: 0pt;</div><div class=\"ql-code-block\" data-language=\"plain\"> &nbsp; &nbsp; &nbsp; &nbsp;line-height: 1.15;</div><div class=\"ql-code-block\" data-language=\"plain\"> &nbsp; &nbsp; &nbsp; &nbsp;orphans: 2;</div><div class=\"ql-code-block\" data-language=\"plain\"> &nbsp; &nbsp; &nbsp; &nbsp;widows: 2;</div><div class=\"ql-code-block\" data-language=\"plain\"> &nbsp; &nbsp; &nbsp; &nbsp;text-align: left</div><div class=\"ql-code-block\" data-language=\"plain\"> &nbsp; &nbsp;}</div><div class=\"ql-code-block\" data-language=\"plain\"><br></div><div class=\"ql-code-block\" data-language=\"plain\"> &nbsp; &nbsp;.c14 {</div><div class=\"ql-code-block\" data-language=\"plain\"> &nbsp; &nbsp; &nbsp; &nbsp;padding-top: 0pt;</div><div class=\"ql-code-block\" data-language=\"plain\"> &nbsp; &nbsp; &nbsp; &nbsp;padding-bottom: 0pt;</div><div class=\"ql-code-block\" data-language=\"plain\"> &nbsp; &nbsp; &nbsp; &nbsp;line-height: 1.0;</div><div class=\"ql-code-block\" data-language=\"plain\"> &nbsp; &nbsp; &nbsp; &nbsp;orphans: 2;</div><div class=\"ql-code-block\" data-language=\"plain\"> &nbsp; &nbsp; &nbsp; &nbsp;widows: 2;</div><div class=\"ql-code-block\" data-language=\"plain\"> &nbsp; &nbsp; &nbsp; &nbsp;text-align: left</div><div class=\"ql-code-block\" data-language=\"plain\"> &nbsp; &nbsp;}</div><div class=\"ql-code-block\" data-language=\"plain\"><br></div><div class=\"ql-code-block\" data-language=\"plain\"> &nbsp; &nbsp;.c17 {</div><div class=\"ql-code-block\" data-language=\"plain\"> &nbsp; &nbsp; &nbsp; &nbsp;padding-top: 14pt;</div><div class=\"ql-code-block\" data-language=\"plain\"> &nbsp; &nbsp; &nbsp; &nbsp;padding-bottom: 4pt;</div><div class=\"ql-code-block\" data-language=\"plain\"> &nbsp; &nbsp; &nbsp; &nbsp;line-height: 1.15;</div><div class=\"ql-code-block\" data-language=\"plain\"> &nbsp; &nbsp; &nbsp; &nbsp;orphans: 2;</div><div class=\"ql-code-block\" data-language=\"plain\"> &nbsp; &nbsp; &nbsp; &nbsp;widows: 2;</div><div class=\"ql-code-block\" data-language=\"plain\"> &nbsp; &nbsp; &nbsp; &nbsp;text-align: center</div><div class=\"ql-code-block\" data-language=\"plain\"> &nbsp; &nbsp;}</div><div class=\"ql-code-block\" data-language=\"plain\"><br></div><div class=\"ql-code-block\" data-language=\"plain\"> &nbsp; &nbsp;.c12 {</div><div class=\"ql-code-block\" data-language=\"plain\"> &nbsp; &nbsp; &nbsp; &nbsp;padding-top: 12pt;</div><div class=\"ql-code-block\" data-language=\"plain\"> &nbsp; &nbsp; &nbsp; &nbsp;padding-bottom: 12pt;</div><div class=\"ql-code-block\" data-language=\"plain\"> &nbsp; &nbsp; &nbsp; &nbsp;line-height: 1.15;</div><div class=\"ql-code-block\" data-language=\"plain\"> &nbsp; &nbsp; &nbsp; &nbsp;orphans: 2;</div><div class=\"ql-code-block\" data-language=\"plain\"> &nbsp; &nbsp; &nbsp; &nbsp;widows: 2;</div><div class=\"ql-code-block\" data-language=\"plain\"> &nbsp; &nbsp; &nbsp; &nbsp;text-align: left</div><div class=\"ql-code-block\" data-language=\"plain\"> &nbsp; &nbsp;}</div><div class=\"ql-code-block\" data-language=\"plain\"><br></div><div class=\"ql-code-block\" data-language=\"plain\"> &nbsp; &nbsp;.c19 {</div><div class=\"ql-code-block\" data-language=\"plain\"> &nbsp; &nbsp; &nbsp; &nbsp;padding-top: 10pt;</div><div class=\"ql-code-block\" data-language=\"plain\"> &nbsp; &nbsp; &nbsp; &nbsp;padding-bottom: 12pt;</div><div class=\"ql-code-block\" data-language=\"plain\"> &nbsp; &nbsp; &nbsp; &nbsp;line-height: 1.15;</div><div class=\"ql-code-block\" data-language=\"plain\"> &nbsp; &nbsp; &nbsp; &nbsp;orphans: 2;</div><div class=\"ql-code-block\" data-language=\"plain\"> &nbsp; &nbsp; &nbsp; &nbsp;widows: 2;</div><div class=\"ql-code-block\" data-language=\"plain\"> &nbsp; &nbsp; &nbsp; &nbsp;text-align: left</div><div class=\"ql-code-block\" data-language=\"plain\"> &nbsp; &nbsp;}</div><div class=\"ql-code-block\" data-language=\"plain\"><br></div><div class=\"ql-code-block\" data-language=\"plain\"> &nbsp; &nbsp;.c10 {</div><div class=\"ql-code-block\" data-language=\"plain\"> &nbsp; &nbsp; &nbsp; &nbsp;padding-top: 12pt;</div><div class=\"ql-code-block\" data-language=\"plain\"> &nbsp; &nbsp; &nbsp; &nbsp;padding-bottom: 0pt;</div><div class=\"ql-code-block\" data-language=\"plain\"> &nbsp; &nbsp; &nbsp; &nbsp;line-height: 1.15;</div><div class=\"ql-code-block\" data-language=\"plain\"> &nbsp; &nbsp; &nbsp; &nbsp;orphans: 2;</div><div class=\"ql-code-block\" data-language=\"plain\"> &nbsp; &nbsp; &nbsp; &nbsp;widows: 2;</div><div class=\"ql-code-block\" data-language=\"plain\"> &nbsp; &nbsp; &nbsp; &nbsp;text-align: left</div><div class=\"ql-code-block\" data-language=\"plain\"> &nbsp; &nbsp;}</div><div class=\"ql-code-block\" data-language=\"plain\"><br></div><div class=\"ql-code-block\" data-language=\"plain\"> &nbsp; &nbsp;.c22 {</div><div class=\"ql-code-block\" data-language=\"plain\"> &nbsp; &nbsp; &nbsp; &nbsp;padding-top: 10pt;</div><div class=\"ql-code-block\" data-language=\"plain\"> &nbsp; &nbsp; &nbsp; &nbsp;padding-bottom: 12pt;</div><div class=\"ql-code-block\" data-language=\"plain\"> &nbsp; &nbsp; &nbsp; &nbsp;line-height: 1.0;</div><div class=\"ql-code-block\" data-language=\"plain\"> &nbsp; &nbsp; &nbsp; &nbsp;orphans: 2;</div><div class=\"ql-code-block\" data-language=\"plain\"> &nbsp; &nbsp; &nbsp; &nbsp;widows: 2;</div><div class=\"ql-code-block\" data-language=\"plain\"> &nbsp; &nbsp; &nbsp; &nbsp;text-align: left</div><div class=\"ql-code-block\" data-language=\"plain\"> &nbsp; &nbsp;}</div><div class=\"ql-code-block\" data-language=\"plain\"><br></div><div class=\"ql-code-block\" data-language=\"plain\"> &nbsp; &nbsp;.c9 {</div><div class=\"ql-code-block\" data-language=\"plain\"> &nbsp; &nbsp; &nbsp; &nbsp;padding-top: 0pt;</div><div class=\"ql-code-block\" data-language=\"plain\"> &nbsp; &nbsp; &nbsp; &nbsp;padding-bottom: 12pt;</div><div class=\"ql-code-block\" data-language=\"plain\"> &nbsp; &nbsp; &nbsp; &nbsp;line-height: 1.15;</div><div class=\"ql-code-block\" data-language=\"plain\"> &nbsp; &nbsp; &nbsp; &nbsp;orphans: 2;</div><div class=\"ql-code-block\" data-language=\"plain\"> &nbsp; &nbsp; &nbsp; &nbsp;widows: 2;</div><div class=\"ql-code-block\" data-language=\"plain\"> &nbsp; &nbsp; &nbsp; &nbsp;text-align: left</div><div class=\"ql-code-block\" data-language=\"plain\"> &nbsp; &nbsp;}</div><div class=\"ql-code-block\" data-language=\"plain\"><br></div><div class=\"ql-code-block\" data-language=\"plain\"> &nbsp; &nbsp;.c6 {</div><div class=\"ql-code-block\" data-language=\"plain\"> &nbsp; &nbsp; &nbsp; &nbsp;color: #000000;</div><div class=\"ql-code-block\" data-language=\"plain\"> &nbsp; &nbsp; &nbsp; &nbsp;text-decoration: none;</div><div class=\"ql-code-block\" data-language=\"plain\"> &nbsp; &nbsp; &nbsp; &nbsp;vertical-align: baseline;</div><div class=\"ql-code-block\" data-language=\"plain\"> &nbsp; &nbsp; &nbsp; &nbsp;font-size: 11pt;</div><div class=\"ql-code-block\" data-language=\"plain\"> &nbsp; &nbsp; &nbsp; &nbsp;font-style: normal</div><div class=\"ql-code-block\" data-language=\"plain\"> &nbsp; &nbsp;}</div><div class=\"ql-code-block\" data-language=\"plain\"><br></div><div class=\"ql-code-block\" data-language=\"plain\"> &nbsp; &nbsp;.c13 {</div><div class=\"ql-code-block\" data-language=\"plain\"> &nbsp; &nbsp; &nbsp; &nbsp;border-spacing: 0;</div><div class=\"ql-code-block\" data-language=\"plain\"> &nbsp; &nbsp; &nbsp; &nbsp;border-collapse: collapse;</div><div class=\"ql-code-block\" data-language=\"plain\"> &nbsp; &nbsp; &nbsp; &nbsp;margin-right: auto</div><div class=\"ql-code-block\" data-language=\"plain\"> &nbsp; &nbsp;}</div><div class=\"ql-code-block\" data-language=\"plain\"><br></div><div class=\"ql-code-block\" data-language=\"plain\"> &nbsp; &nbsp;.c3 {</div><div class=\"ql-code-block\" data-language=\"plain\"> &nbsp; &nbsp; &nbsp; &nbsp;background-color: #ffffff;</div><div class=\"ql-code-block\" data-language=\"plain\"> &nbsp; &nbsp; &nbsp; &nbsp;font-family: \"Roboto\";</div><div class=\"ql-code-block\" data-language=\"plain\"> &nbsp; &nbsp; &nbsp; &nbsp;font-weight: 400</div><div class=\"ql-code-block\" data-language=\"plain\"> &nbsp; &nbsp;}</div><div class=\"ql-code-block\" data-language=\"plain\"><br></div><div class=\"ql-code-block\" data-language=\"plain\"> &nbsp; &nbsp;.c11 {</div><div class=\"ql-code-block\" data-language=\"plain\"> &nbsp; &nbsp; &nbsp; &nbsp;background-color: #ffff00;</div><div class=\"ql-code-block\" data-language=\"plain\"> &nbsp; &nbsp; &nbsp; &nbsp;font-weight: 400;</div><div class=\"ql-code-block\" data-language=\"plain\"> &nbsp; &nbsp; &nbsp; &nbsp;font-family: \"Roboto\"</div><div class=\"ql-code-block\" data-language=\"plain\"> &nbsp; &nbsp;}</div><div class=\"ql-code-block\" data-language=\"plain\"><br></div><div class=\"ql-code-block\" data-language=\"plain\"> &nbsp; &nbsp;.c23 {</div><div class=\"ql-code-block\" data-language=\"plain\"> &nbsp; &nbsp; &nbsp; &nbsp;background-color: #ffffff;</div><div class=\"ql-code-block\" data-language=\"plain\"> &nbsp; &nbsp; &nbsp; &nbsp;max-width: 468pt;</div><div class=\"ql-code-block\" data-language=\"plain\"> &nbsp; &nbsp; &nbsp; &nbsp;padding: 72pt 72pt 72pt 72pt</div><div class=\"ql-code-block\" data-language=\"plain\"> &nbsp; &nbsp;}</div><div class=\"ql-code-block\" data-language=\"plain\"><br></div><div class=\"ql-code-block\" data-language=\"plain\"> &nbsp; &nbsp;.c2 {</div><div class=\"ql-code-block\" data-language=\"plain\"> &nbsp; &nbsp; &nbsp; &nbsp;background-color: #ffffff;</div><div class=\"ql-code-block\" data-language=\"plain\"> &nbsp; &nbsp; &nbsp; &nbsp;font-family: \"Roboto\";</div><div class=\"ql-code-block\" data-language=\"plain\"> &nbsp; &nbsp; &nbsp; &nbsp;font-weight: 700</div><div class=\"ql-code-block\" data-language=\"plain\"> &nbsp; &nbsp;}</div><div class=\"ql-code-block\" data-language=\"plain\"><br></div><div class=\"ql-code-block\" data-language=\"plain\"> &nbsp; &nbsp;.c16 {</div><div class=\"ql-code-block\" data-language=\"plain\"> &nbsp; &nbsp; &nbsp; &nbsp;padding: 0;</div><div class=\"ql-code-block\" data-language=\"plain\"> &nbsp; &nbsp; &nbsp; &nbsp;margin: 0</div><div class=\"ql-code-block\" data-language=\"plain\"> &nbsp; &nbsp;}</div><div class=\"ql-code-block\" data-language=\"plain\"><br></div><div class=\"ql-code-block\" data-language=\"plain\"> &nbsp; &nbsp;.c20 {</div><div class=\"ql-code-block\" data-language=\"plain\"> &nbsp; &nbsp; &nbsp; &nbsp;margin-right: 36pt;</div><div class=\"ql-code-block\" data-language=\"plain\"> &nbsp; &nbsp; &nbsp; &nbsp;padding-right: 0pt</div><div class=\"ql-code-block\" data-language=\"plain\"> &nbsp; &nbsp;}</div><div class=\"ql-code-block\" data-language=\"plain\"><br></div><div class=\"ql-code-block\" data-language=\"plain\"> &nbsp; &nbsp;.c24 {</div><div class=\"ql-code-block\" data-language=\"plain\"> &nbsp; &nbsp; &nbsp; &nbsp;font-weight: 400;</div><div class=\"ql-code-block\" data-language=\"plain\"> &nbsp; &nbsp; &nbsp; &nbsp;font-family: \"Arial\"</div><div class=\"ql-code-block\" data-language=\"plain\"> &nbsp; &nbsp;}</div><div class=\"ql-code-block\" data-language=\"plain\"><br></div><div class=\"ql-code-block\" data-language=\"plain\"> &nbsp; &nbsp;.c7 {</div><div class=\"ql-code-block\" data-language=\"plain\"> &nbsp; &nbsp; &nbsp; &nbsp;font-size: 11pt;</div><div class=\"ql-code-block\" data-language=\"plain\"> &nbsp; &nbsp; &nbsp; &nbsp;color: #000000</div><div class=\"ql-code-block\" data-language=\"plain\"> &nbsp; &nbsp;}</div><div class=\"ql-code-block\" data-language=\"plain\"><br></div><div class=\"ql-code-block\" data-language=\"plain\"> &nbsp; &nbsp;.c15 {</div><div class=\"ql-code-block\" data-language=\"plain\"> &nbsp; &nbsp; &nbsp; &nbsp;height: 11pt</div><div class=\"ql-code-block\" data-language=\"plain\"> &nbsp; &nbsp;}</div><div class=\"ql-code-block\" data-language=\"plain\"><br></div><div class=\"ql-code-block\" data-language=\"plain\"> &nbsp; &nbsp;.c21 {</div><div class=\"ql-code-block\" data-language=\"plain\"> &nbsp; &nbsp; &nbsp; &nbsp;height: 92.8pt</div><div class=\"ql-code-block\" data-language=\"plain\"> &nbsp; &nbsp;}</div><div class=\"ql-code-block\" data-language=\"plain\"><br></div><div class=\"ql-code-block\" data-language=\"plain\"> &nbsp; &nbsp;.c18 {</div><div class=\"ql-code-block\" data-language=\"plain\"> &nbsp; &nbsp; &nbsp; &nbsp;height: 0pt</div><div class=\"ql-code-block\" data-language=\"plain\"> &nbsp; &nbsp;}</div><div class=\"ql-code-block\" data-language=\"plain\"><br></div><div class=\"ql-code-block\" data-language=\"plain\"> &nbsp; &nbsp;.title {</div><div class=\"ql-code-block\" data-language=\"plain\"> &nbsp; &nbsp; &nbsp; &nbsp;padding-top: 0pt;</div><div class=\"ql-code-block\" data-language=\"plain\"> &nbsp; &nbsp; &nbsp; &nbsp;color: #000000;</div><div class=\"ql-code-block\" data-language=\"plain\"> &nbsp; &nbsp; &nbsp; &nbsp;font-size: 26pt;</div><div class=\"ql-code-block\" data-language=\"plain\"> &nbsp; &nbsp; &nbsp; &nbsp;padding-bottom: 3pt;</div><div class=\"ql-code-block\" data-language=\"plain\"> &nbsp; &nbsp; &nbsp; &nbsp;font-family: \"Arial\";</div><div class=\"ql-code-block\" data-language=\"plain\"> &nbsp; &nbsp; &nbsp; &nbsp;line-height: 1.15;</div><div class=\"ql-code-block\" data-language=\"plain\"> &nbsp; &nbsp; &nbsp; &nbsp;page-break-after: avoid;</div><div class=\"ql-code-block\" data-language=\"plain\"> &nbsp; &nbsp; &nbsp; &nbsp;orphans: 2;</div><div class=\"ql-code-block\" data-language=\"plain\"> &nbsp; &nbsp; &nbsp; &nbsp;widows: 2;</div><div class=\"ql-code-block\" data-language=\"plain\"> &nbsp; &nbsp; &nbsp; &nbsp;text-align: left</div><div class=\"ql-code-block\" data-language=\"plain\"> &nbsp; &nbsp;}</div><div class=\"ql-code-block\" data-language=\"plain\"><br></div><div class=\"ql-code-block\" data-language=\"plain\"> &nbsp; &nbsp;.subtitle {</div><div class=\"ql-code-block\" data-language=\"plain\"> &nbsp; &nbsp; &nbsp; &nbsp;padding-top: 0pt;</div><div class=\"ql-code-block\" data-language=\"plain\"> &nbsp; &nbsp; &nbsp; &nbsp;color: #666666;</div><div class=\"ql-code-block\" data-language=\"plain\"> &nbsp; &nbsp; &nbsp; &nbsp;font-size: 15pt;</div><div class=\"ql-code-block\" data-language=\"plain\"> &nbsp; &nbsp; &nbsp; &nbsp;padding-bottom: 16pt;</div><div class=\"ql-code-block\" data-language=\"plain\"> &nbsp; &nbsp; &nbsp; &nbsp;font-family: \"Arial\";</div><div class=\"ql-code-block\" data-language=\"plain\"> &nbsp; &nbsp; &nbsp; &nbsp;line-height: 1.15;</div><div class=\"ql-code-block\" data-language=\"plain\"> &nbsp; &nbsp; &nbsp; &nbsp;page-break-after: avoid;</div><div class=\"ql-code-block\" data-language=\"plain\"> &nbsp; &nbsp; &nbsp; &nbsp;orphans: 2;</div><div class=\"ql-code-block\" data-language=\"plain\"> &nbsp; &nbsp; &nbsp; &nbsp;widows: 2;</div><div class=\"ql-code-block\" data-language=\"plain\"> &nbsp; &nbsp; &nbsp; &nbsp;text-align: left</div><div class=\"ql-code-block\" data-language=\"plain\"> &nbsp; &nbsp;}</div><div class=\"ql-code-block\" data-language=\"plain\"><br></div><div class=\"ql-code-block\" data-language=\"plain\"> &nbsp; &nbsp;li {</div><div class=\"ql-code-block\" data-language=\"plain\"> &nbsp; &nbsp; &nbsp; &nbsp;color: #000000;</div><div class=\"ql-code-block\" data-language=\"plain\"> &nbsp; &nbsp; &nbsp; &nbsp;font-size: 11pt;</div><div class=\"ql-code-block\" data-language=\"plain\"> &nbsp; &nbsp; &nbsp; &nbsp;font-family: \"Arial\"</div><div class=\"ql-code-block\" data-language=\"plain\"> &nbsp; &nbsp;}</div><div class=\"ql-code-block\" data-language=\"plain\"><br></div><div class=\"ql-code-block\" data-language=\"plain\"> &nbsp; &nbsp;p {</div><div class=\"ql-code-block\" data-language=\"plain\"> &nbsp; &nbsp; &nbsp; &nbsp;margin: 0;</div><div class=\"ql-code-block\" data-language=\"plain\"> &nbsp; &nbsp; &nbsp; &nbsp;color: #000000;</div><div class=\"ql-code-block\" data-language=\"plain\"> &nbsp; &nbsp; &nbsp; &nbsp;font-size: 11pt;</div><div class=\"ql-code-block\" data-language=\"plain\"> &nbsp; &nbsp; &nbsp; &nbsp;font-family: \"Arial\"</div><div class=\"ql-code-block\" data-language=\"plain\"> &nbsp; &nbsp;}</div><div class=\"ql-code-block\" data-language=\"plain\"><br></div><div class=\"ql-code-block\" data-language=\"plain\"> &nbsp; &nbsp;h1 {</div><div class=\"ql-code-block\" data-language=\"plain\"> &nbsp; &nbsp; &nbsp; &nbsp;padding-top: 20pt;</div><div class=\"ql-code-block\" data-language=\"plain\"> &nbsp; &nbsp; &nbsp; &nbsp;color: #000000;</div><div class=\"ql-code-block\" data-language=\"plain\"> &nbsp; &nbsp; &nbsp; &nbsp;font-size: 20pt;</div><div class=\"ql-code-block\" data-language=\"plain\"> &nbsp; &nbsp; &nbsp; &nbsp;padding-bottom: 6pt;</div><div class=\"ql-code-block\" data-language=\"plain\"> &nbsp; &nbsp; &nbsp; &nbsp;font-family: \"Arial\";</div><div class=\"ql-code-block\" data-language=\"plain\"> &nbsp; &nbsp; &nbsp; &nbsp;line-height: 1.15;</div><div class=\"ql-code-block\" data-language=\"plain\"> &nbsp; &nbsp; &nbsp; &nbsp;page-break-after: avoid;</div><div class=\"ql-code-block\" data-language=\"plain\"> &nbsp; &nbsp; &nbsp; &nbsp;orphans: 2;</div><div class=\"ql-code-block\" data-language=\"plain\"> &nbsp; &nbsp; &nbsp; &nbsp;widows: 2;</div><div class=\"ql-code-block\" data-language=\"plain\"> &nbsp; &nbsp; &nbsp; &nbsp;text-align: left</div><div class=\"ql-code-block\" data-language=\"plain\"> &nbsp; &nbsp;}</div><div class=\"ql-code-block\" data-language=\"plain\"><br></div><div class=\"ql-code-block\" data-language=\"plain\"> &nbsp; &nbsp;h2 {</div><div class=\"ql-code-block\" data-language=\"plain\"> &nbsp; &nbsp; &nbsp; &nbsp;padding-top: 18pt;</div><div class=\"ql-code-block\" data-language=\"plain\"> &nbsp; &nbsp; &nbsp; &nbsp;color: #000000;</div><div class=\"ql-code-block\" data-language=\"plain\"> &nbsp; &nbsp; &nbsp; &nbsp;font-size: 16pt;</div><div class=\"ql-code-block\" data-language=\"plain\"> &nbsp; &nbsp; &nbsp; &nbsp;padding-bottom: 6pt;</div><div class=\"ql-code-block\" data-language=\"plain\"> &nbsp; &nbsp; &nbsp; &nbsp;font-family: \"Arial\";</div><div class=\"ql-code-block\" data-language=\"plain\"> &nbsp; &nbsp; &nbsp; &nbsp;line-height: 1.15;</div><div class=\"ql-code-block\" data-language=\"plain\"> &nbsp; &nbsp; &nbsp; &nbsp;page-break-after: avoid;</div><div class=\"ql-code-block\" data-language=\"plain\"> &nbsp; &nbsp; &nbsp; &nbsp;orphans: 2;</div><div class=\"ql-code-block\" data-language=\"plain\"> &nbsp; &nbsp; &nbsp; &nbsp;widows: 2;</div><div class=\"ql-code-block\" data-language=\"plain\"> &nbsp; &nbsp; &nbsp; &nbsp;text-align: left</div><div class=\"ql-code-block\" data-language=\"plain\"> &nbsp; &nbsp;}</div><div class=\"ql-code-block\" data-language=\"plain\"><br></div><div class=\"ql-code-block\" data-language=\"plain\"> &nbsp; &nbsp;h3 {</div><div class=\"ql-code-block\" data-language=\"plain\"> &nbsp; &nbsp; &nbsp; &nbsp;padding-top: 16pt;</div><div class=\"ql-code-block\" data-language=\"plain\"> &nbsp; &nbsp; &nbsp; &nbsp;color: #434343;</div><div class=\"ql-code-block\" data-language=\"plain\"> &nbsp; &nbsp; &nbsp; &nbsp;font-size: 14pt;</div><div class=\"ql-code-block\" data-language=\"plain\"> &nbsp; &nbsp; &nbsp; &nbsp;padding-bottom: 4pt;</div><div class=\"ql-code-block\" data-language=\"plain\"> &nbsp; &nbsp; &nbsp; &nbsp;font-family: \"Arial\";</div><div class=\"ql-code-block\" data-language=\"plain\"> &nbsp; &nbsp; &nbsp; &nbsp;line-height: 1.15;</div><div class=\"ql-code-block\" data-language=\"plain\"> &nbsp; &nbsp; &nbsp; &nbsp;page-break-after: avoid;</div><div class=\"ql-code-block\" data-language=\"plain\"> &nbsp; &nbsp; &nbsp; &nbsp;orphans: 2;</div><div class=\"ql-code-block\" data-language=\"plain\"> &nbsp; &nbsp; &nbsp; &nbsp;widows: 2;</div><div class=\"ql-code-block\" data-language=\"plain\"> &nbsp; &nbsp; &nbsp; &nbsp;text-align: left</div><div class=\"ql-code-block\" data-language=\"plain\"> &nbsp; &nbsp;}</div><div class=\"ql-code-block\" data-language=\"plain\"><br></div><div class=\"ql-code-block\" data-language=\"plain\"> &nbsp; &nbsp;h4 {</div><div class=\"ql-code-block\" data-language=\"plain\"> &nbsp; &nbsp; &nbsp; &nbsp;padding-top: 14pt;</div><div class=\"ql-code-block\" data-language=\"plain\"> &nbsp; &nbsp; &nbsp; &nbsp;color: #666666;</div><div class=\"ql-code-block\" data-language=\"plain\"> &nbsp; &nbsp; &nbsp; &nbsp;font-size: 12pt;</div><div class=\"ql-code-block\" data-language=\"plain\"> &nbsp; &nbsp; &nbsp; &nbsp;padding-bottom: 4pt;</div><div class=\"ql-code-block\" data-language=\"plain\"> &nbsp; &nbsp; &nbsp; &nbsp;font-family: \"Arial\";</div><div class=\"ql-code-block\" data-language=\"plain\"> &nbsp; &nbsp; &nbsp; &nbsp;line-height: 1.15;</div><div class=\"ql-code-block\" data-language=\"plain\"> &nbsp; &nbsp; &nbsp; &nbsp;page-break-after: avoid;</div><div class=\"ql-code-block\" data-language=\"plain\"> &nbsp; &nbsp; &nbsp; &nbsp;orphans: 2;</div><div class=\"ql-code-block\" data-language=\"plain\"> &nbsp; &nbsp; &nbsp; &nbsp;widows: 2;</div><div class=\"ql-code-block\" data-language=\"plain\"> &nbsp; &nbsp; &nbsp; &nbsp;text-align: left</div><div class=\"ql-code-block\" data-language=\"plain\"> &nbsp; &nbsp;}</div><div class=\"ql-code-block\" data-language=\"plain\"><br></div><div class=\"ql-code-block\" data-language=\"plain\"> &nbsp; &nbsp;h5 {</div><div class=\"ql-code-block\" data-language=\"plain\"> &nbsp; &nbsp; &nbsp; &nbsp;padding-top: 12pt;</div><div class=\"ql-code-block\" data-language=\"plain\"> &nbsp; &nbsp; &nbsp; &nbsp;color: #666666;</div><div class=\"ql-code-block\" data-language=\"plain\"> &nbsp; &nbsp; &nbsp; &nbsp;font-size: 11pt;</div><div class=\"ql-code-block\" data-language=\"plain\"> &nbsp; &nbsp; &nbsp; &nbsp;padding-bottom: 4pt;</div><div class=\"ql-code-block\" data-language=\"plain\"> &nbsp; &nbsp; &nbsp; &nbsp;font-family: \"Arial\";</div><div class=\"ql-code-block\" data-language=\"plain\"> &nbsp; &nbsp; &nbsp; &nbsp;line-height: 1.15;</div><div class=\"ql-code-block\" data-language=\"plain\"> &nbsp; &nbsp; &nbsp; &nbsp;page-break-after: avoid;</div><div class=\"ql-code-block\" data-language=\"plain\"> &nbsp; &nbsp; &nbsp; &nbsp;orphans: 2;</div><div class=\"ql-code-block\" data-language=\"plain\"> &nbsp; &nbsp; &nbsp; &nbsp;widows: 2;</div><div class=\"ql-code-block\" data-language=\"plain\"> &nbsp; &nbsp; &nbsp; &nbsp;text-align: left</div><div class=\"ql-code-block\" data-language=\"plain\"> &nbsp; &nbsp;}</div><div class=\"ql-code-block\" data-language=\"plain\"><br></div><div class=\"ql-code-block\" data-language=\"plain\"> &nbsp; &nbsp;h6 {</div><div class=\"ql-code-block\" data-language=\"plain\"> &nbsp; &nbsp; &nbsp; &nbsp;padding-top: 12pt;</div><div class=\"ql-code-block\" data-language=\"plain\"> &nbsp; &nbsp; &nbsp; &nbsp;color: #666666;</div><div class=\"ql-code-block\" data-language=\"plain\"> &nbsp; &nbsp; &nbsp; &nbsp;font-size: 11pt;</div><div class=\"ql-code-block\" data-language=\"plain\"> &nbsp; &nbsp; &nbsp; &nbsp;padding-bottom: 4pt;</div><div class=\"ql-code-block\" data-language=\"plain\"> &nbsp; &nbsp; &nbsp; &nbsp;font-family: \"Arial\";</div><div class=\"ql-code-block\" data-language=\"plain\"> &nbsp; &nbsp; &nbsp; &nbsp;line-height: 1.15;</div><div class=\"ql-code-block\" data-language=\"plain\"> &nbsp; &nbsp; &nbsp; &nbsp;page-break-after: avoid;</div><div class=\"ql-code-block\" data-language=\"plain\"> &nbsp; &nbsp; &nbsp; &nbsp;font-style: italic;</div><div class=\"ql-code-block\" data-language=\"plain\"> &nbsp; &nbsp; &nbsp; &nbsp;orphans: 2;</div><div class=\"ql-code-block\" data-language=\"plain\"> &nbsp; &nbsp; &nbsp; &nbsp;widows: 2;</div><div class=\"ql-code-block\" data-language=\"plain\"> &nbsp; &nbsp; &nbsp; &nbsp;text-align: left</div><div class=\"ql-code-block\" data-language=\"plain\"> &nbsp; &nbsp;}&lt;/style&gt;</div><div class=\"ql-code-block\" data-language=\"plain\">&lt;/head&gt;</div><div class=\"ql-code-block\" data-language=\"plain\">&lt;body class=\"c23 doc-content\"&gt;&lt;p class=\"c1 c15\"&gt;&lt;span class=\"c6 c11\"&gt;&lt;/span&gt;&lt;/p&gt;</div><div class=\"ql-code-block\" data-language=\"plain\">&lt;p class=\"c1\"&gt;&lt;span class=\"c6 c11\"&gt;1. Email sent to employee after employee applies for leave:&lt;/span&gt;&lt;/p&gt;</div><div class=\"ql-code-block\" data-language=\"plain\">&lt;h3 class=\"c17\" dir=\"rtl\" id=\"h.v3m65weartrd\"&gt;&lt;span class=\"c6 c2\"&gt;&amp;#1575;&amp;#1604;&amp;#1605;&amp;#1608;&amp;#1590;&amp;#1608;&amp;#1593;: &amp;#1578;&amp;#1601;&amp;#1575;&amp;#1589;&amp;#1610;&amp;#1604; &amp;#1591;&amp;#1604;&amp;#1576; &amp;#1575;&amp;#1604;&amp;#1573;&amp;#1580;&amp;#1575;&amp;#1586;&amp;#1577; - &amp;#1578;&amp;#1571;&amp;#1603;&amp;#1610;&amp;#1583;&lt;/span&gt;</div><div class=\"ql-code-block\" data-language=\"plain\">&lt;/h3&gt;</div><div class=\"ql-code-block\" data-language=\"plain\">&lt;h3 class=\"c17\" id=\"h.8l0bmkijyjg5\"&gt;&lt;span class=\"c2 c7\"&gt;Subject: Leave Application Details &amp;ndash; Confirmation&lt;/span&gt;</div><div class=\"ql-code-block\" data-language=\"plain\">&lt;/h3&gt;</div><div class=\"ql-code-block\" data-language=\"plain\">&lt;p class=\"c1 c15\"&gt;&lt;span class=\"c6 c11\"&gt;&lt;/span&gt;&lt;/p&gt;</div><div class=\"ql-code-block\" data-language=\"plain\">&lt;table class=\"c13\"&gt;</div><div class=\"ql-code-block\" data-language=\"plain\"> &nbsp; &nbsp;&lt;tr class=\"c21\"&gt;</div><div class=\"ql-code-block\" data-language=\"plain\"> &nbsp; &nbsp; &nbsp; &nbsp;&lt;td class=\"c8\" colspan=\"1\" rowspan=\"1\"&gt;&lt;p class=\"c12\"&gt;&lt;span class=\"c0\"&gt;Dear [Employee Name],&lt;/span&gt;&lt;/p&gt;</div><div class=\"ql-code-block\" data-language=\"plain\"> &nbsp; &nbsp; &nbsp; &nbsp; &nbsp; &nbsp;&lt;p class=\"c9\"&gt;&lt;span class=\"c0\"&gt;You have applied for a Leave Application, and the details are below:&lt;/span&gt;</div><div class=\"ql-code-block\" data-language=\"plain\"> &nbsp; &nbsp; &nbsp; &nbsp; &nbsp; &nbsp;&lt;/p&gt;&lt;/td&gt;</div><div class=\"ql-code-block\" data-language=\"plain\"> &nbsp; &nbsp; &nbsp; &nbsp;&lt;td class=\"c8\" colspan=\"1\" rowspan=\"1\"&gt;&lt;p class=\"c12\" dir=\"rtl\"&gt;&lt;span class=\"c0\"&gt;&amp;#1593;&amp;#1586;&amp;#1610;&amp;#1586;&amp;#1610;/&amp;#1593;&amp;#1586;&amp;#1610;&amp;#1586;&amp;#1578;&amp;#1610; [&amp;#1575;&amp;#1587;&amp;#1605; &amp;#1575;&amp;#1604;&amp;#1605;&amp;#1608;&amp;#1592;&amp;#1601;]&lt;/span&gt;</div><div class=\"ql-code-block\" data-language=\"plain\"> &nbsp; &nbsp; &nbsp; &nbsp;&lt;/p&gt;</div><div class=\"ql-code-block\" data-language=\"plain\"> &nbsp; &nbsp; &nbsp; &nbsp; &nbsp; &nbsp;&lt;p class=\"c10\" dir=\"rtl\"&gt;&lt;span class=\"c0\"&gt;&amp;#1604;&amp;#1602;&amp;#1583; &amp;#1602;&amp;#1583;&amp;#1605;&amp;#1578; &amp;#1591;&amp;#1604;&amp;#1576; &amp;#1573;&amp;#1580;&amp;#1575;&amp;#1586;&amp;#1577;&amp;#1548; &amp;#1608;&amp;#1575;&amp;#1604;&amp;#1578;&amp;#1601;&amp;#1575;&amp;#1589;&amp;#1610;&amp;#1604; &amp;#1571;&amp;#1583;&amp;#1606;&amp;#1575;&amp;#1607;:&lt;/span&gt;</div><div class=\"ql-code-block\" data-language=\"plain\"> &nbsp; &nbsp; &nbsp; &nbsp; &nbsp; &nbsp;&lt;/p&gt;&lt;/td&gt;</div><div class=\"ql-code-block\" data-language=\"plain\"> &nbsp; &nbsp;&lt;/tr&gt;</div><div class=\"ql-code-block\" data-language=\"plain\"> &nbsp; &nbsp;&lt;tr class=\"c18\"&gt;</div><div class=\"ql-code-block\" data-language=\"plain\"> &nbsp; &nbsp; &nbsp; &nbsp;&lt;td class=\"c8\" colspan=\"1\" rowspan=\"1\"&gt;&lt;p class=\"c9\"&gt;&lt;span class=\"c2\"&gt;Employee Name:&lt;/span&gt;&lt;span class=\"c3\"&gt;&amp;nbsp;John Doe&lt;br&gt;&lt;/span&gt;&lt;span</div><div class=\"ql-code-block\" data-language=\"plain\"> &nbsp; &nbsp; &nbsp; &nbsp; &nbsp; &nbsp; &nbsp; &nbsp;class=\"c2\"&gt;Employee ID:&lt;/span&gt;&lt;span class=\"c3\"&gt;&amp;nbsp;123456&lt;br&gt;&lt;/span&gt;&lt;span</div><div class=\"ql-code-block\" data-language=\"plain\"> &nbsp; &nbsp; &nbsp; &nbsp; &nbsp; &nbsp; &nbsp; &nbsp;class=\"c2\"&gt;Leave Type:&lt;/span&gt;&lt;span class=\"c0\"&gt;&amp;nbsp;Annual Leave&lt;/span&gt;&lt;/p&gt;</div><div class=\"ql-code-block\" data-language=\"plain\"> &nbsp; &nbsp; &nbsp; &nbsp; &nbsp; &nbsp;&lt;p class=\"c12\"&gt;&lt;span class=\"c2 c6\"&gt;Leave Duration Request:&lt;/span&gt;&lt;/p&gt;</div><div class=\"ql-code-block\" data-language=\"plain\"> &nbsp; &nbsp; &nbsp; &nbsp; &nbsp; &nbsp;&lt;ul class=\"c16 lst-kix_8uqlpnf6wjap-0 start\"&gt;</div><div class=\"ql-code-block\" data-language=\"plain\"> &nbsp; &nbsp; &nbsp; &nbsp; &nbsp; &nbsp; &nbsp; &nbsp;&lt;li class=\"c5 li-bullet-0\"&gt;&lt;span class=\"c0\"&gt;Start Date: 2024-10-01&lt;/span&gt;&lt;/li&gt;</div><div class=\"ql-code-block\" data-language=\"plain\"> &nbsp; &nbsp; &nbsp; &nbsp; &nbsp; &nbsp; &nbsp; &nbsp;&lt;li class=\"c5 li-bullet-0\"&gt;&lt;span class=\"c0\"&gt;End Date: 2024-10-10&lt;/span&gt;&lt;/li&gt;</div><div class=\"ql-code-block\" data-language=\"plain\"> &nbsp; &nbsp; &nbsp; &nbsp; &nbsp; &nbsp; &nbsp; &nbsp;&lt;li class=\"c5 li-bullet-0\"&gt;&lt;span class=\"c0\"&gt;Total Days: 10 Days&lt;/span&gt;&lt;/li&gt;</div><div class=\"ql-code-block\" data-language=\"plain\"> &nbsp; &nbsp; &nbsp; &nbsp; &nbsp; &nbsp;&lt;/ul&gt;</div><div class=\"ql-code-block\" data-language=\"plain\"> &nbsp; &nbsp; &nbsp; &nbsp; &nbsp; &nbsp;&lt;p class=\"c12\"&gt;&lt;span class=\"c2\"&gt;Date of Application:&lt;/span&gt;&lt;span class=\"c3\"&gt;&amp;nbsp;2024-09-20&lt;br&gt;&lt;/span&gt;&lt;span</div><div class=\"ql-code-block\" data-language=\"plain\"> &nbsp; &nbsp; &nbsp; &nbsp; &nbsp; &nbsp; &nbsp; &nbsp; &nbsp; &nbsp;class=\"c2\"&gt;Leave Approver:&lt;/span&gt;&lt;span class=\"c3\"&gt;&amp;nbsp;Sarah Johnson&lt;br&gt;&lt;/span&gt;&lt;span class=\"c2\"&gt;Status:&lt;/span&gt;&lt;span</div><div class=\"ql-code-block\" data-language=\"plain\"> &nbsp; &nbsp; &nbsp; &nbsp; &nbsp; &nbsp; &nbsp; &nbsp; &nbsp; &nbsp;class=\"c3\"&gt;&amp;nbsp;Pending Approval&lt;/span&gt;&lt;/p&gt;&lt;/td&gt;</div><div class=\"ql-code-block\" data-language=\"plain\"> &nbsp; &nbsp; &nbsp; &nbsp;&lt;td class=\"c8\" colspan=\"1\" rowspan=\"1\"&gt;&lt;p class=\"c1\" dir=\"rtl\"&gt;&lt;span class=\"c2\"&gt;&amp;#1575;&amp;#1587;&amp;#1605; &amp;#1575;&amp;#1604;&amp;#1605;&amp;#1608;&amp;#1592;&amp;#1601;&lt;/span&gt;&lt;span</div><div class=\"ql-code-block\" data-language=\"plain\"> &nbsp; &nbsp; &nbsp; &nbsp; &nbsp; &nbsp; &nbsp; &nbsp;class=\"c3\"&gt;: &amp;#1580;&amp;#1608;&amp;#1606; &amp;#1583;&amp;#1608;&lt;br&gt;&lt;/span&gt;&lt;span class=\"c2\"&gt;&amp;#1585;&amp;#1602;&amp;#1605; &amp;#1575;&amp;#1604;&amp;#1605;&amp;#1608;&amp;#1592;&amp;#1601;&lt;/span&gt;&lt;span</div><div class=\"ql-code-block\" data-language=\"plain\"> &nbsp; &nbsp; &nbsp; &nbsp; &nbsp; &nbsp; &nbsp; &nbsp;class=\"c3\"&gt;: 123456&lt;br&gt;&lt;/span&gt;&lt;span class=\"c2\"&gt;&amp;#1606;&amp;#1608;&amp;#1593; &amp;#1575;&amp;#1604;&amp;#1573;&amp;#1580;&amp;#1575;&amp;#1586;&amp;#1577;&lt;/span&gt;&lt;span</div><div class=\"ql-code-block\" data-language=\"plain\"> &nbsp; &nbsp; &nbsp; &nbsp; &nbsp; &nbsp; &nbsp; &nbsp;class=\"c0\"&gt;: &amp;#1573;&amp;#1580;&amp;#1575;&amp;#1586;&amp;#1577; &amp;#1587;&amp;#1606;&amp;#1608;&amp;#1610;&amp;#1577;&lt;/span&gt;&lt;/p&gt;</div><div class=\"ql-code-block\" data-language=\"plain\"> &nbsp; &nbsp; &nbsp; &nbsp; &nbsp; &nbsp;&lt;p class=\"c1\" dir=\"rtl\"&gt;&lt;span class=\"c3\"&gt;&lt;br&gt;&lt;/span&gt;&lt;span class=\"c6 c2\"&gt;&amp;#1605;&amp;#1583;&amp;#1577; &amp;#1575;&amp;#1604;&amp;#1573;&amp;#1580;&amp;#1575;&amp;#1586;&amp;#1577; &amp;#1575;&amp;#1604;&amp;#1605;&amp;#1591;&amp;#1604;&amp;#1608;&amp;#1576;&amp;#1577;:&lt;/span&gt;</div><div class=\"ql-code-block\" data-language=\"plain\"> &nbsp; &nbsp; &nbsp; &nbsp; &nbsp; &nbsp;&lt;/p&gt;</div><div class=\"ql-code-block\" data-language=\"plain\"> &nbsp; &nbsp; &nbsp; &nbsp; &nbsp; &nbsp;&lt;ul class=\"c16 lst-kix_g0ncveqa373c-0 start\"&gt;</div><div class=\"ql-code-block\" data-language=\"plain\"> &nbsp; &nbsp; &nbsp; &nbsp; &nbsp; &nbsp; &nbsp; &nbsp;&lt;li class=\"c19 c20 li-bullet-1\" dir=\"rtl\"&gt;&lt;span class=\"c2\"&gt;&amp;#1578;&amp;#1575;&amp;#1585;&amp;#1610;&amp;#1582; &amp;#1575;&amp;#1604;&amp;#1576;&amp;#1583;&amp;#1569;:&lt;/span&gt;&lt;span</div><div class=\"ql-code-block\" data-language=\"plain\"> &nbsp; &nbsp; &nbsp; &nbsp; &nbsp; &nbsp; &nbsp; &nbsp; &nbsp; &nbsp; &nbsp; &nbsp;class=\"c0\"&gt;&amp;nbsp;2024-10-01&lt;/span&gt;&lt;/li&gt;</div><div class=\"ql-code-block\" data-language=\"plain\"> &nbsp; &nbsp; &nbsp; &nbsp; &nbsp; &nbsp; &nbsp; &nbsp;&lt;li class=\"c19 c20 li-bullet-2\" dir=\"rtl\"&gt;&lt;span class=\"c2\"&gt;&amp;#1578;&amp;#1575;&amp;#1585;&amp;#1610;&amp;#1582; &amp;#1575;&amp;#1604;&amp;#1575;&amp;#1606;&amp;#1578;&amp;#1607;&amp;#1575;&amp;#1569;:&lt;/span&gt;&lt;span</div><div class=\"ql-code-block\" data-language=\"plain\"> &nbsp; &nbsp; &nbsp; &nbsp; &nbsp; &nbsp; &nbsp; &nbsp; &nbsp; &nbsp; &nbsp; &nbsp;class=\"c0\"&gt;&amp;nbsp;2024-10-10&lt;/span&gt;&lt;/li&gt;</div><div class=\"ql-code-block\" data-language=\"plain\"> &nbsp; &nbsp; &nbsp; &nbsp; &nbsp; &nbsp; &nbsp; &nbsp;&lt;li class=\"c20 c22 li-bullet-1\" dir=\"rtl\"&gt;&lt;span class=\"c2\"&gt;&amp;#1573;&amp;#1580;&amp;#1605;&amp;#1575;&amp;#1604;&amp;#1610; &amp;#1575;&amp;#1604;&amp;#1571;&amp;#1610;&amp;#1575;&amp;#1605;:&lt;/span&gt;&lt;span</div><div class=\"ql-code-block\" data-language=\"plain\"> &nbsp; &nbsp; &nbsp; &nbsp; &nbsp; &nbsp; &nbsp; &nbsp; &nbsp; &nbsp; &nbsp; &nbsp;class=\"c0\"&gt;&amp;nbsp;10 &amp;#1571;&amp;#1610;&amp;#1575;&amp;#1605;&lt;/span&gt;&lt;/li&gt;</div><div class=\"ql-code-block\" data-language=\"plain\"> &nbsp; &nbsp; &nbsp; &nbsp; &nbsp; &nbsp;&lt;/ul&gt;</div><div class=\"ql-code-block\" data-language=\"plain\"> &nbsp; &nbsp; &nbsp; &nbsp; &nbsp; &nbsp;&lt;p class=\"c19\" dir=\"rtl\"&gt;&lt;span class=\"c2\"&gt;&amp;#1578;&amp;#1575;&amp;#1585;&amp;#1610;&amp;#1582; &amp;#1575;&amp;#1604;&amp;#1578;&amp;#1602;&amp;#1583;&amp;#1610;&amp;#1605;&lt;/span&gt;&lt;span</div><div class=\"ql-code-block\" data-language=\"plain\"> &nbsp; &nbsp; &nbsp; &nbsp; &nbsp; &nbsp; &nbsp; &nbsp; &nbsp; &nbsp;class=\"c3\"&gt;: 2024-09-20&lt;br&gt;&lt;/span&gt;&lt;span</div><div class=\"ql-code-block\" data-language=\"plain\"> &nbsp; &nbsp; &nbsp; &nbsp; &nbsp; &nbsp; &nbsp; &nbsp; &nbsp; &nbsp;class=\"c2\"&gt;&amp;#1575;&amp;#1604;&amp;#1605;&amp;#1608;&amp;#1575;&amp;#1601;&amp;#1602;&lt;/span&gt;&lt;span class=\"c3\"&gt;: &amp;#1587;&amp;#1575;&amp;#1585;&amp;#1577; &amp;#1580;&amp;#1608;&amp;#1606;&amp;#1587;&amp;#1608;&amp;#1606;&lt;br&gt;&lt;/span&gt;&lt;span</div><div class=\"ql-code-block\" data-language=\"plain\"> &nbsp; &nbsp; &nbsp; &nbsp; &nbsp; &nbsp; &nbsp; &nbsp; &nbsp; &nbsp;class=\"c2\"&gt;&amp;#1575;&amp;#1604;&amp;#1581;&amp;#1575;&amp;#1604;&amp;#1577;&lt;/span&gt;&lt;span class=\"c3\"&gt;: &amp;#1602;&amp;#1610;&amp;#1583; &amp;#1575;&amp;#1604;&amp;#1605;&amp;#1585;&amp;#1575;&amp;#1580;&amp;#1593;&amp;#1577;&lt;/span&gt;</div><div class=\"ql-code-block\" data-language=\"plain\"> &nbsp; &nbsp; &nbsp; &nbsp; &nbsp; &nbsp;&lt;/p&gt;&lt;/td&gt;</div><div class=\"ql-code-block\" data-language=\"plain\"> &nbsp; &nbsp;&lt;/tr&gt;</div><div class=\"ql-code-block\" data-language=\"plain\"> &nbsp; &nbsp;&lt;tr class=\"c18\"&gt;</div><div class=\"ql-code-block\" data-language=\"plain\"> &nbsp; &nbsp; &nbsp; &nbsp;&lt;td class=\"c8\" colspan=\"1\" rowspan=\"1\"&gt;&lt;p class=\"c9\"&gt;&lt;span class=\"c0\"&gt;Please note that your leave request is currently under review. You will be notified once your leave has been approved or if any further action is required.&lt;/span&gt;</div><div class=\"ql-code-block\" data-language=\"plain\"> &nbsp; &nbsp; &nbsp; &nbsp;&lt;/p&gt;</div><div class=\"ql-code-block\" data-language=\"plain\"> &nbsp; &nbsp; &nbsp; &nbsp; &nbsp; &nbsp;&lt;p class=\"c12\"&gt;&lt;span class=\"c0\"&gt;If you have any questions or need to make adjustments to your request, please contact your line manager.&lt;/span&gt;</div><div class=\"ql-code-block\" data-language=\"plain\"> &nbsp; &nbsp; &nbsp; &nbsp; &nbsp; &nbsp;&lt;/p&gt;</div><div class=\"ql-code-block\" data-language=\"plain\"> &nbsp; &nbsp; &nbsp; &nbsp; &nbsp; &nbsp;&lt;p class=\"c12\"&gt;&lt;span class=\"c3\"&gt;Thank you,&lt;br&gt;One Facilities Management&lt;/span&gt;&lt;/p&gt;&lt;/td&gt;</div><div class=\"ql-code-block\" data-language=\"plain\"> &nbsp; &nbsp; &nbsp; &nbsp;&lt;td class=\"c8\" colspan=\"1\" rowspan=\"1\"&gt;&lt;p class=\"c9\" dir=\"rtl\"&gt;&lt;span class=\"c0\"&gt;&amp;#1610;&amp;#1585;&amp;#1580;&amp;#1609; &amp;#1605;&amp;#1604;&amp;#1575;&amp;#1581;&amp;#1592;&amp;#1577; &amp;#1571;&amp;#1606; &amp;#1591;&amp;#1604;&amp;#1576; &amp;#1573;&amp;#1580;&amp;#1575;&amp;#1586;&amp;#1578;&amp;#1603; &amp;#1602;&amp;#1610;&amp;#1583; &amp;#1575;&amp;#1604;&amp;#1605;&amp;#1585;&amp;#1575;&amp;#1580;&amp;#1593;&amp;#1577; &amp;#1581;&amp;#1575;&amp;#1604;&amp;#1610;&amp;#1611;&amp;#1575;. &amp;#1587;&amp;#1578;&amp;#1578;&amp;#1604;&amp;#1602;&amp;#1609; &amp;#1573;&amp;#1588;&amp;#1593;&amp;#1575;&amp;#1585;&amp;#1611;&amp;#1575; &amp;#1576;&amp;#1605;&amp;#1580;&amp;#1585;&amp;#1583; &amp;#1575;&amp;#1604;&amp;#1605;&amp;#1608;&amp;#1575;&amp;#1601;&amp;#1602;&amp;#1577; &amp;#1593;&amp;#1604;&amp;#1609; &amp;#1573;&amp;#1580;&amp;#1575;&amp;#1586;&amp;#1578;&amp;#1603; &amp;#1571;&amp;#1608; &amp;#1573;&amp;#1584;&amp;#1575; &amp;#1603;&amp;#1575;&amp;#1606;&amp;#1578; &amp;#1607;&amp;#1606;&amp;#1575;&amp;#1603; &amp;#1581;&amp;#1575;&amp;#1580;&amp;#1577; &amp;#1604;&amp;#1571;&amp;#1610; &amp;#1573;&amp;#1580;&amp;#1585;&amp;#1575;&amp;#1569; &amp;#1573;&amp;#1590;&amp;#1575;&amp;#1601;&amp;#1610;.&lt;/span&gt;</div><div class=\"ql-code-block\" data-language=\"plain\"> &nbsp; &nbsp; &nbsp; &nbsp;&lt;/p&gt;</div><div class=\"ql-code-block\" data-language=\"plain\"> &nbsp; &nbsp; &nbsp; &nbsp; &nbsp; &nbsp;&lt;p class=\"c12\" dir=\"rtl\"&gt;&lt;span class=\"c0\"&gt;&lt;br&gt;&amp;#1573;&amp;#1584;&amp;#1575; &amp;#1603;&amp;#1575;&amp;#1606; &amp;#1604;&amp;#1583;&amp;#1610;&amp;#1603; &amp;#1571;&amp;#1610; &amp;#1571;&amp;#1587;&amp;#1574;&amp;#1604;&amp;#1577; &amp;#1571;&amp;#1608; &amp;#1578;&amp;#1581;&amp;#1578;&amp;#1575;&amp;#1580; &amp;#1573;&amp;#1604;&amp;#1609; &amp;#1573;&amp;#1580;&amp;#1585;&amp;#1575;&amp;#1569; &amp;#1578;&amp;#1593;&amp;#1583;&amp;#1610;&amp;#1604;&amp;#1575;&amp;#1578; &amp;#1593;&amp;#1604;&amp;#1609; &amp;#1591;&amp;#1604;&amp;#1576;&amp;#1603;&amp;#1548; &amp;#1610;&amp;#1585;&amp;#1580;&amp;#1609; &amp;#1575;&amp;#1604;&amp;#1575;&amp;#1578;&amp;#1589;&amp;#1575;&amp;#1604; &amp;#1576;&amp;#1575;&amp;#1604;&amp;#1605;&amp;#1583;&amp;#1610;&amp;#1585; &amp;#1575;&amp;#1604;&amp;#1605;&amp;#1576;&amp;#1575;&amp;#1588;&amp;#1585; &amp;#1575;&amp;#1604;&amp;#1582;&amp;#1575;&amp;#1589; &amp;#1576;&amp;#1603;.&lt;/span&gt;</div><div class=\"ql-code-block\" data-language=\"plain\"> &nbsp; &nbsp; &nbsp; &nbsp; &nbsp; &nbsp;&lt;/p&gt;</div><div class=\"ql-code-block\" data-language=\"plain\"> &nbsp; &nbsp; &nbsp; &nbsp; &nbsp; &nbsp;&lt;p class=\"c14 c15\" dir=\"rtl\"&gt;&lt;span class=\"c0\"&gt;&lt;/span&gt;&lt;/p&gt;</div><div class=\"ql-code-block\" data-language=\"plain\"> &nbsp; &nbsp; &nbsp; &nbsp; &nbsp; &nbsp;&lt;p class=\"c14\" dir=\"rtl\"&gt;&lt;span class=\"c0\"&gt;&amp;#1588;&amp;#1603;&amp;#1585;&amp;#1575;&amp;#1611; &amp;#1604;&amp;#1603;&amp;#1548;&lt;/span&gt;</div><div class=\"ql-code-block\" data-language=\"plain\"> &nbsp; &nbsp; &nbsp; &nbsp; &nbsp; &nbsp;&lt;/p&gt;</div><div class=\"ql-code-block\" data-language=\"plain\"> &nbsp; &nbsp; &nbsp; &nbsp; &nbsp; &nbsp;&lt;p class=\"c14\" dir=\"rtl\"&gt;&lt;span class=\"c0\"&gt;&amp;#1588;&amp;#1585;&amp;#1603;&amp;#1577; &amp;#1608;&amp;#1606; &amp;#1604;&amp;#1573;&amp;#1583;&amp;#1575;&amp;#1585;&amp;#1577; &amp;#1575;&amp;#1604;&amp;#1605;&amp;#1585;&amp;#1575;&amp;#1601;&amp;#1602;&lt;/span&gt;</div><div class=\"ql-code-block\" data-language=\"plain\"> &nbsp; &nbsp; &nbsp; &nbsp; &nbsp; &nbsp;&lt;/p&gt;&lt;/td&gt;</div><div class=\"ql-code-block\" data-language=\"plain\"> &nbsp; &nbsp;&lt;/tr&gt;</div><div class=\"ql-code-block\" data-language=\"plain\">&lt;/table&gt;</div><div class=\"ql-code-block\" data-language=\"plain\">&lt;p class=\"c1 c15\"&gt;&lt;span class=\"c6 c24\"&gt;&lt;/span&gt;&lt;/p&gt;&lt;/body&gt;</div><div class=\"ql-code-block\" data-language=\"plain\">&lt;/html&gt;</div></pre></div>",
  "response_html": "<!DOCTYPE html>\n<html lang=\"en\">\n<head>\n    <meta charset=\"UTF-8\">\n    <meta name=\"viewport\" content=\"width=device-width, initial-scale=1.0\">\n    <title>Leave Application Confirmation</title>\n\n    <style>\n        @import url('https://fonts.googleapis.com/css2?family=PT+Sans:wght@400;700&family=Sen:wght@400;700&family=Cairo:wght@400;700&family=Readex+Pro:wght@400;700&family=Noto+Naskh+Arabic:wght@400&display=swap');\n\n        body {\n            font-family: Arial, sans-serif;\n            background-color: #f1f1f1;\n            color: #111;\n            margin: 0;\n            padding: 20px;\n        }\n\n        /* Title Styles (English) */\n        .title {\n            font-family: 'Sen', sans-serif;\n            font-size: 36px;\n            font-style: italic;\n            font-weight: bold;\n            color: #000;\n            text-align: center;\n        }\n\n        /* Subtitle Styles (English) */\n        .subtitle {\n            font-family: 'Sen', sans-serif;\n            font-size: 18px;\n            font-style: italic;\n            color: #A9A9A9; /* Dark Gray 3 */\n        }\n\n        /* Heading 1 (English) */\n        h1 {\n            font-family: 'PT Sans', sans-serif;\n            font-size: 22px;\n            font-weight: bold;\n            font-style: italic;\n            color: #000;\n        }\n\n        /* Heading 2 (English) */\n        h2 {\n            font-family: 'PT Sans', sans-serif;\n            font-size: 18px;\n            font-weight: bold;\n            font-style: italic;\n            color: #000;\n        }\n\n        /* Heading 3 (English) */\n        h3 {\n            font-family: 'PT Sans', sans-serif;\n            font-size: 18px;\n            font-weight: bold;\n            font-style: italic;\n            color: #696969; /* Dark Gray 4 */\n        }\n\n        /* Heading 4 (English) */\n        h4 {\n            font-family: 'PT Sans', sans-serif;\n            font-size: 18px;\n            font-weight: bold;\n            font-style: italic;\n            color: #A9A9A9; /* Dark Gray 3 */\n        }\n\n        /* Heading 5 (English) */\n        h5 {\n            font-family: 'PT Sans', sans-serif;\n            font-size: 18px;\n            font-weight: bold;\n            font-style: italic;\n            color: #BEBEBE; /* Dark Gray 2 */\n        }\n\n        /* Normal Body Text (English) */\n        p {\n            font-family: Arial, sans-serif;\n            font-size: 10px;\n            color: #000;\n        }\n\n        /* Title Styles (Arabic) */\n        .title-ar {\n            font-family: 'Cairo', sans-serif;\n            font-size: 36px;\n            font-style: italic;\n            font-weight: bold;\n            color: #000;\n            text-align: center;\n        }\n\n        /* Heading 1 (Arabic) */\n        h1.arabic {\n            font-family: 'Readex Pro', sans-serif;\n            font-size: 22px;\n            font-weight: bold;\n            font-style: italic;\n            color: #000;\n        }\n\n        /* Heading 2 (Arabic) */\n        h2.arabic {\n            font-family: 'Readex Pro', sans-serif;\n            font-size: 18px;\n            font-weight: bold;\n            font-style: italic;\n            color: #000;\n        }\n\n        /* Heading 3 (Arabic) */\n        h3.arabic {\n            font-family: 'Readex Pro', sans-serif;\n            font-size: 18px;\n            font-weight: bold;\n            font-style: italic;\n            color: #000;\n        }\n\n        /* Heading 4 (Arabic) */\n        h4.arabic {\n            font-family: 'Readex Pro', sans-serif;\n            font-size: 18px;\n            font-weight: bold;\n            font-style: italic;\n            color: #000;\n        }\n\n        /* Normal Body Text (Arabic) */\n        p.arabic {\n            font-family: 'Noto Naskh Arabic', sans-serif;\n            font-size: 10px;\n            color: #000;\n        }\n\n        /* Layout */\n        .container {\n            display: flex;\n            justify-content: space-between;\n            border: 0px solid #fff;\n            padding: 0;\n        }\n\n        .section {\n            width: 50%;\n            box-sizing: border-box;\n            padding: 0;\n        }\n\n        .english {\n            text-align: left;\n        }\n\n        .arabic {\n            text-align: right;\n            direction: rtl;\n        }\n\n        .section p {\n            margin: 5px 0;\n            line-height: 1.6;\n        }\n\n        .details {\n            font-weight: bold;\n        }\n\n        ul li {\n            margin-bottom: 5px;\n        }\n\n        .bordered {\n            border: 0px solid #fff;\n            padding: 10px;\n            min-height: 100px;\n        }\n    </style>\n</head>\n<body>\n\n    <!-- Subject Lines -->\n    <div class=\"subject\">\n        <h3 dir=\"rtl\" class=\"title-ar\">:    - </h3>\n        <h3 class=\"title\">Subject: Leave Application Details  Confirmation</h3>\n    </div>\n\n    <!-- Two-column container for English and Arabic sections -->\n    <div class=\"container\">\n        <!-- English Section -->\n        <div class=\"section english\">\n            <div class=\"bordered\">\n                <p>Dear {{ employee_name }},</p>\n                <p>You have applied for a Leave Application, and the details are below:</p>\n            </div>\n\n            <div class=\"bordered\">\n                <p class=\"details\">Employee Name: {{ employee_name }}</p>\n                <p class=\"details\">Employee ID: {{ employee }}</p>\n                <p class=\"details\">Leave Type: {{ leave_type }}</p>\n                <p class=\"details\">Leave Duration Request:</p>\n                <ul>\n                    <li>Start Date: {{ from_date }}</li>\n                    <li>End Date: {{ to_date }}</li>\n                    <li>Total Days: {{ total_leave_days }} Days</li>\n                </ul>\n                <p class=\"details\">Date of Application: {{ posting_date }}</p>\n                <p class=\"details\">Leave Approver: {{ leave_approver_in_english }}</p>\n                <p class=\"details\">Status: {{ status }}</p>\n            </div>\n\n            <div class=\"bordered\">\n                <p>Please note that your leave request is currently under review. You will be notified once your leave has been approved or if any further action is required.</p>\n                <p>If you have any questions or need to make adjustments to your request, please contact your line manager.</p>\n                <p>Thank you,<br>{{ company }}</p>\n            </div>\n        </div>\n\n        <!-- Arabic Section -->\n        <div class=\"section arabic\">\n            <div class=\"bordered\">\n                <p class=\"arabic\">/ {{ employee_name_in_arabic }},</p>\n                <p class=\"arabic\">     :</p>\n            </div>\n\n            <div class=\"bordered\">\n                <p class=\"details arabic\"> : {{ employee_name_in_arabic }}</p>\n                <p class=\"details arabic\"> : {{ employee }}</p>\n                <p class=\"details arabic\"> : {{ leave_type_in_arabic }}</p>\n                <p class=\"details arabic\">  :</p>\n                <ul>\n                    <li class=\"arabic\"> : {{ from_date }}</li>\n                    <li class=\"arabic\"> : {{ to_date }}</li>\n                    {% if total_leave_days == 1 %}\n                        <li class=\"arabic\"> : {{ total_leave_days }} </li>\n                    {% elif total_leave_days == 2 %}\n                        <li class=\"arabic\"> : {{ total_leave_days }} </li>\n                    {% else %}\n                        <li class=\"arabic\"> : {{ total_leave_days }} </li>\n                    {% endif %}\n                </ul>\n                <p class=\"details arabic\"> : {{ posting_date }}</p>\n                <p class=\"details arabic\">: {{ leave_approver_in_arabic }}</p>\n                <p class=\"details arabic\">: {{ status_in_arabic }}</p>\n            </div>\n\n            <div class=\"bordered\">\n                <p class=\"arabic\">         .              .</p>\n                <p class=\"arabic\">                 .</p>\n                <p class=\"arabic\"> <br>   </p>\n            </div>\n        </div>\n    </div>\n\n</body>\n</html>\n",
  "selling": 0,
  "subject": "Leave Application - Status",
  "use_html": 1
 },
 {
  "buying": 0,
  "docstatus": 0,
  "doctype": "Email Template",
  "hr": 0,
  "modified": "2023-04-17 23:23:24.686953",
  "name": "Dispatch Notification",
  "response": "<h1>Dispatch Notification</h1>\n<h3>Details:</h3>\n<table class=\"table table-bordered small\" style=\"max-width: 500px;\">\n    <tbody>\n        <tr>\n            <td>Customer's Name</td>\n            <td>{{ customer }}</td>\n        </tr>\n        <tr>\n            <td>Contact's Name</td>\n            <td>{{ first_name }} {{ last_name }}</td>\n        </tr>\n        <tr>\n            <td>Address Name</td>\n            <td>{{ address }}</td>\n        </tr>\n        <tr>\n            <td>Address Details</td>\n            <td>{{ customer_address }}</td>\n        </tr>\n        <tr>\n            <td>Order Number</td>\n            <td>{{ delivery_note }}</td>\n        </tr>\n        <tr>\n            <td>Order Total</td>\n            <td>{{ grand_total }}</td>\n        </tr>\n        <tr>\n            <td>Departure Time</td>\n            <td>{{ departure_time }}</td>\n        </tr>\n        <tr>\n            <td>Estimated Arrival</td>\n            <td>{{ estimated_arrival }}</td>\n        </tr>\n        <tr>\n            <td>Driver's Name</td>\n            <td>{{ driver_name }}</td>\n        </tr>\n        <tr>\n            <td>Driver's Number</td>\n            <td>{{ cell_number }}</td>\n        </tr>\n        <tr>\n            <td>Vehicle Number</td>\n            <td>{{ vehicle }}</td>\n        </tr>\n    </tbody>\n</table>",
  "response_html": null,
  "selling": 0,
  "subject": "Order Dispatch - Status",
  "use_html": 0
 },
 {
  "buying": 0,
  "docstatus": 0,
  "doctype": "Email Template",
  "hr": 0,
  "modified": "2021-11-24 15:05:53.708319",
  "name": "Interview Reminder",
  "response": "<h1>Interview Reminder</h1>\n\n<p>\n\tInterview: {{name}} is scheduled on {{scheduled_on}} from {{from_time}} to {{to_time}}\n</p>\n",
  "response_html": null,
  "selling": 0,
  "subject": "Interview Reminder",
  "use_html": 0
 },
 {
  "buying": 0,
  "docstatus": 0,
  "doctype": "Email Template",
  "hr": 0,
  "modified": "2023-04-17 23:22:42.276479",
  "name": "Interview Feedback Reminder",
  "response": "<h1>Interview Feedback Reminder</h1>\n\n<p>\n\tInterview Feedback for Interview {{ name }} is not submitted yet. Please submit your feedback. Thank you, good day!\n</p>\n",
  "response_html": null,
  "selling": 0,
  "subject": "Interview Feedback",
  "use_html": 0
 },
 {
  "buying": 0,
  "docstatus": 0,
  "doctype": "Email Template",
  "hr": 0,
  "modified": "2023-04-17 23:21:20.559285",
  "name": "Work Contract Approval",
  "response": "<div class=\"ql-editor read-mode\"><p>The {{job_applicant}} need approval. The Work Contract is below. Kindly, take action to approve this.</p></div>",
  "response_html": "\nHello,\n    The Work Contract <a href=\"http://localhost:8000/app/work-contract/{{name}}\">{{name}}</a> needs approval. Kindly, take the necessary action.\n<br><br>\n<a class=\"btn btn-success\" style=\"background-color:green;text-align:center;\"  href=\"http://localhost:8000/api/method/one_fm.hiring.doctype.work_contract.work_contract.autorized_signatory_approve?docname={{name}}\">\n    Approve</a>\n<a class=\"btn btn-success\" style=\"background-color:red;text-align:center;\" href=\"http://localhost:8000/api/method/one_fm.hiring.doctype.work_contract.work_contract.autorized_signatory_reject?docname={{name}}\">\n    Reject</a>",
  "selling": 0,
  "subject": "Work Contract - Approval",
  "use_html": 1
 },
 {
  "buying": 0,
  "docstatus": 0,
  "doctype": "Email Template",
  "hr": 0,
  "modified": "2022-02-21 15:51:34.389490",
  "name": "Default Template",
  "response": null,
  "response_html": "<div class=\"gray-container text-center\">\n\t<div style=\"margin-top: 15px\">\n\t\t<p class=\"text-muted\">{{ message }}</p>\n\t</div>\n</div>",
  "selling": 0,
  "subject": "{{subject}}",
  "use_html": 1
 },
 {
  "buying": 0,
  "docstatus": 0,
  "doctype": "Email Template",
  "hr": 0,
  "modified": "2024-10-22 20:51:41.160916",
  "name": "Leave Employee Approval Notification",
  "response": null,
  "response_html": "<!DOCTYPE html>\n<html lang=\"ar\">\n<head>\n    <meta charset=\"UTF-8\">\n    <meta name=\"viewport\" content=\"width=device-width, initial-scale=1.0\">\n    <title>Leave Application Approved  Confirmation</title>\n\n    <style>\n        @import url('https://fonts.googleapis.com/css2?family=PT+Sans:wght@400;700&family=Sen:wght@400;700&family=Cairo:wght@400;700&family=Readex+Pro:wght@400;700&family=Noto+Naskh+Arabic:wght@400&display=swap');\n\n        body {\n            font-family: Arial, sans-serif;\n            background-color: #f1f1f1;\n            color: #111;\n            margin: 0;\n            padding: 20px;\n        }\n\n        /* Title Styles (English) */\n        .title {\n            font-family: 'Sen', sans-serif;\n            font-size: 36px;\n            font-style: italic;\n            font-weight: bold;\n            color: #000;\n            text-align: center;\n        }\n\n        /* Subtitle Styles (English) */\n        .subtitle {\n            font-family: 'Sen', sans-serif;\n            font-size: 18px;\n            font-style: italic;\n            color: #A9A9A9; /* Dark Gray 3 */\n        }\n\n        /* Heading 1 (English) */\n        h1 {\n            font-family: 'PT Sans', sans-serif;\n            font-size: 22px;\n            font-weight: bold;\n            font-style: italic;\n            color: #000;\n        }\n\n        /* Heading 2 (English) */\n        h2 {\n            font-family: 'PT Sans', sans-serif;\n            font-size: 18px;\n            font-weight: bold;\n            font-style: italic;\n            color: #000;\n        }\n\n        /* Heading 3 (English) */\n        h3 {\n            font-family: 'PT Sans', sans-serif;\n            font-size: 18px;\n            font-weight: bold;\n            font-style: italic;\n            color: #696969; /* Dark Gray 4 */\n        }\n\n        /* Heading 4 (English) */\n        h4 {\n            font-family: 'PT Sans', sans-serif;\n            font-size: 18px;\n            font-weight: bold;\n            font-style: italic;\n            color: #A9A9A9; /* Dark Gray 3 */\n        }\n\n        /* Normal Body Text (English) */\n        p {\n            font-family: Arial, sans-serif;\n            font-size: 10px;\n            color: #000;\n        }\n\n        /* Title Styles (Arabic) */\n        .title-ar {\n            font-family: 'Cairo', sans-serif;\n            font-size: 36px;\n            font-style: italic;\n            font-weight: bold;\n            color: #000;\n            text-align: center;\n        }\n\n        /* Heading 1 (Arabic) */\n        h1.arabic {\n            font-family: 'Readex Pro', sans-serif;\n            font-size: 22px;\n            font-weight: bold;\n            font-style: italic;\n            color: #000;\n        }\n\n        /* Heading 2 (Arabic) */\n        h2.arabic {\n            font-family: 'Readex Pro', sans-serif;\n            font-size: 18px;\n            font-weight: bold;\n            font-style: italic;\n            color: #000;\n        }\n\n        /* Heading 3 (Arabic) */\n        h3.arabic {\n            font-family: 'Readex Pro', sans-serif;\n            font-size: 18px;\n            font-weight: bold;\n            font-style: italic;\n            color: #000;\n        }\n\n        /* Heading 4 (Arabic) */\n        h4.arabic {\n            font-family: 'Readex Pro', sans-serif;\n            font-size: 18px;\n            font-weight: bold;\n            font-style: italic;\n            color: #000;\n        }\n\n        /* Normal Body Text (Arabic) */\n        p.arabic {\n            font-family: 'Noto Naskh Arabic', sans-serif;\n            font-size: 10px;\n            color: #000;\n        }\n\n        /* Layout */\n        .container {\n            display: flex;\n            justify-content: space-between;\n            border: 0px solid #fff;\n            padding: 0;\n        }\n\n        .section {\n            width: 50%;\n            box-sizing: border-box;\n            padding: 0;\n        }\n\n        .english {\n            text-align: left;\n        }\n\n        .arabic {\n            text-align: right;\n            direction: rtl;\n        }\n\n        .section p {\n            margin: 5px 0;\n            line-height: 1.6;\n        }\n\n        .details {\n            font-weight: bold;\n        }\n\n        ul li {\n            margin-bottom: 5px;\n        }\n\n        .bordered {\n            border: 0px solid #fff;\n            padding: 10px;\n            min-height: 100px;\n        }\n\n        /* Center Align the Subject Lines */\n        .subject-container {\n            text-align: center;\n        }\n    </style>\n</head>\n<body>\n\n    <!-- Subject Lines -->\n    <div class=\"subject-container\">\n        <h1 class=\"title-ar\">:       </h1>\n        <h1 class=\"title\">Subject: Leave Application Approved  Confirmation</h1>\n    </div>\n\n    <div class=\"container bordered\">\n        <div class=\"section english\">\n            <p>Dear {{ employee_name }},</p>\n            <p>Your leave application has been successfully approved by your line manager. Below are the confirmed details of your leave:</p>\n        </div>\n        <div class=\"section arabic\">\n            <p>/ {{ employee_name_in_arabic }}</p>\n            <p>          .     :</p>\n        </div>\n    </div>\n\n    <div class=\"container bordered\">\n        <div class=\"section english\">\n            <p><strong class=\"details\">Employee Name:</strong> {{ employee_name }}</p>\n            <p><strong class=\"details\">Employee ID:</strong> {{ employee }}</p>\n            <p><strong class=\"details\">Leave Type:</strong> {{ leave_type }}/p>\n            <p><strong class=\"details\">Leave Duration Request:</strong></p>\n            <ul>\n                <li><strong>Start Date:</strong> {{ from_date }}</li>\n                <li><strong>End Date:</strong> {{ to_date }}</li>\n                <li><strong>Total Days:</strong> {{ total_leave_days }} Days</li>\n            </ul>\n            <p><strong class=\"details\">Date of Application:</strong> {{ posting_date }}</p>\n            <p><strong class=\"details\">Approved By:</strong> {{ leave_approver_in_english }}</p>\n        </div>\n        <div class=\"section arabic\">\n            <p><strong class=\"details\"> :</strong> {{ employee_name_in_arabic }}</p>\n            <p><strong class=\"details\"> :</strong> {{ employee }}</p>\n            <p><strong class=\"details\"> :</strong> {{ leave_type_in_arabic }}</p>\n            <p><strong class=\"details\">  :</strong></p>\n            <ul>\n                <li><strong> :</strong> {{ from_date }}</li>\n                <li><strong> :</strong> {{ to_date }}</li>\n                <li><strong> :</strong>{{ total_leave_days }} </li>\n            </ul>\n            <p><strong class=\"details\"> :</strong> {{ posting_date }}</p>\n            <p><strong class=\"details\"> :</strong> {{ leave_approver_in_arabic }}</p>\n        </div>\n    </div>\n\n    <div class=\"container bordered\">\n        <div class=\"section english\">\n            <p>Please sign your leave application form to confirm the leave date. If there are any changes or additional requirements, please contact your line manager.</p>\n        </div>\n        <div class=\"section arabic\">\n            <p>         .             .</p>\n        </div>\n    </div>\n\n    <div class=\"container bordered\">\n        <div class=\"section english\">\n            <p>Thank you,<br>One Facilities Management</p>\n        </div>\n        <div class=\"section arabic\">\n            <p> </p>\n            <p>   </p>\n        </div>\n    </div>\n\n</body>\n</html>\n",
  "selling": 0,
  "subject": "Leave Employee Approval Notification",
  "use_html": 1
 }
]