{
 "custom_fields": [
  {
   "_assign": null,
   "_comments": null,
   "_liked_by": null,
   "_user_tags": null,
   "allow_in_quick_entry": 0,
   "allow_on_submit": 0,
   "bold": 0,
   "collapsible": 0,
   "collapsible_depends_on": null,
   "columns": 0,
   "creation": "2020-09-08 09:57:53.741787",
   "default": null,
   "depends_on": null,
   "description": null,
   "docstatus": 0,
   "dt": "Price List",
   "fetch_from": null,
   "fetch_if_empty": 0,
   "fieldname": "restaurant_menu",
   "fieldtype": "Link",
   "hidden": 0,
   "idx": 6,
   "ignore_user_permissions": 0,
   "ignore_xss_filter": 0,
   "in_global_search": 0,
   "in_list_view": 0,
   "in_standard_filter": 0,
   "insert_after": "currency",
   "label": "Restaurant Menu",
   "length": 0,
   "modified": "2019-10-22 08:39:15.642360",
   "modified_by": "Administrator",
   "name": "Price List-restaurant_menu",
   "no_copy": 0,
   "options": "Restaurant Menu",
   "owner": "Administrator",
   "parent": null,
   "parentfield": null,
   "parenttype": null,
   "permlevel": 0,
   "precision": "",
   "print_hide": 0,
   "print_hide_if_no_value": 0,
   "print_width": null,
   "read_only": 0,
   "report_hide": 0,
   "reqd": 0,
   "search_index": 0,
   "translatable": 0,
   "unique": 0,
   "width": null
  },
  {
   "_assign": null,
   "_comments": null,
   "_liked_by": null,
   "_user_tags": null,
   "allow_in_quick_entry": 0,
   "allow_on_submit": 0,
   "bold": 0,
   "collapsible": 0,
   "collapsible_depends_on": null,
   "columns": 0,
   "creation": "2020-09-11 12:07:37.986156",
   "default": null,
   "depends_on": null,
   "description": null,
   "docstatus": 0,
   "dt": "Price List",
   "fetch_from": null,
   "fetch_if_empty": 0,
   "fieldname": "project",
   "fieldtype": "Link",
   "hidden": 0,
   "idx": 3,
   "ignore_user_permissions": 0,
   "ignore_xss_filter": 0,
   "in_global_search": 0,
   "in_list_view": 0,
   "in_standard_filter": 0,
   "insert_after": "price_list_name",
   "label": "Project",
   "length": 0,
   "modified": "2020-09-11 12:07:37.986156",
   "modified_by": "Administrator",
   "name": "Price List-project",
   "no_copy": 0,
   "options": "Project",
   "owner": "Administrator",
   "parent": null,
   "parentfield": null,
   "parenttype": null,
   "permlevel": 0,
   "precision": "",
   "print_hide": 0,
   "print_hide_if_no_value": 0,
   "print_width": null,
   "read_only": 0,
   "report_hide": 0,
   "reqd": 0,
   "search_index": 0,
   "translatable": 0,
   "unique": 0,
   "width": null
  }
 ],
 "custom_perms": [],
 "doctype": "Price List",
 "property_setters": [],
 "sync_on_migrate": 1
}