{
 "aggregate_function_based_on": "",
 "color": "#CB2929",
 "creation": "2023-10-30 13:30:23.277961",
 "docstatus": 0,
 "doctype": "Number Card",
 "document_type": "Attendance Check",
 "dynamic_filters_json": "[]",
 "filters_json": "[[\"Attendance Check\",\"attendance_status\",\"=\",\"Absent\",false],[\"Attendance Check\",\"docstatus\",\"=\",\"1\",false],[\"Attendance Check\",\"date\",\"Timespan\",\"this month\",false]]",
 "function": "Count",
 "idx": 0,
 "is_public": 1,
 "is_standard": 1,
 "label": "AC - Absent (This Month)",
 "modified": "2023-10-30 16:10:22.904335",
 "modified_by": "e.olayinka@one-fm.com",
 "module": "One Fm",
 "name": "AC - Absent (This Month)",
 "owner": "e.olayinka@one-fm.com",
 "parent_document_type": "",
 "report_function": "Sum",
 "show_percentage_stats": 1,
 "stats_time_interval": "Monthly",
 "type": "Document Type"
}